{"packId":"unicode-indopak-16","version":"v1","pageNumber":246,"verses":[{"id":1683,"verseKey":"12:87","chapterId":12,"pageNumber":246,"juzNumber":13,"hizbNumber":25,"rubElHizbNumber":98,"textUthmani":"يَـٰبَنِىَّ ٱذْهَبُوا۟ فَتَحَسَّسُوا۟ مِن يُوسُفَ وَأَخِيهِ وَلَا تَا۟يْـَٔسُوا۟ مِن رَّوْحِ ٱللَّهِ ۖ إِنَّهُۥ لَا يَا۟يْـَٔسُ مِن رَّوْحِ ٱللَّهِ إِلَّا ٱلْقَوْمُ ٱلْكَـٰفِرُونَ","textIndopak":"يٰبَنِىَّ اذۡهَبُوۡا فَتَحَسَّسُوۡا مِنۡ يُّوۡسُفَ وَاَخِيۡهِ وَلَا تَايۡــَٔسُوۡا مِنۡ رَّوۡحِ اللّٰهِ​ؕ اِنَّهٗ لَا يَايۡــَٔسُ مِنۡ رَّوۡحِ اللّٰهِ اِلَّا الۡقَوۡمُ الۡكٰفِرُوۡنَ‏","textUthmaniTajweed":"يَ<tajweed class=madda_normal>ـٰ</tajweed>بَنِىَّ <tajweed class=ham_wasl>ٱ</tajweed>ذْهَبُو<tajweed class=slnt>اْ</tajweed> فَتَحَسَّسُو<tajweed class=slnt>اْ</tajweed> م<tajweed class=idgham_ghunnah>ِن ي</tajweed>ُوسُفَ وَأَخِيهِ وَلَا تَ<tajweed class=slnt>اْ</tajweed>يْــَٔسُو<tajweed class=slnt>اْ</tajweed> م<tajweed class=idgham_wo_ghunnah>ِن ر</tajweed>َّوْحِ <tajweed class=ham_wasl>ٱ</tajweed>للَّهِ‌ۖ إِ<tajweed class=ghunnah>نّ</tajweed>َهُ<tajweed class=madda_normal>ۥ</tajweed> لَا يَ<tajweed class=slnt>اْ</tajweed>يْــَٔسُ م<tajweed class=idgham_wo_ghunnah>ِن ر</tajweed>َّوْحِ <tajweed class=ham_wasl>ٱ</tajweed>للَّهِ إِلَّا <tajweed class=ham_wasl>ٱ</tajweed>لْقَوْمُ <tajweed class=ham_wasl>ٱ</tajweed>لْكَ<tajweed class=madda_normal>ـٰ</tajweed>فِر<tajweed class=madda_permissible>ُو</tajweed>نَ <span class=end>٨٧</span>","words":[{"id":67048,"verseKey":"12:87","pageNumber":246,"lineNumber":1,"position":1,"charType":"word","location":"12:87:1","textUthmani":"يَـٰبَنِىَّ","textQpcHafs":"يَٰبَنِيَّ","textIndopak":"يٰبَنِىَّ","codeV1":"ﭑ","codeV2":"ﱁ"},{"id":67049,"verseKey":"12:87","pageNumber":246,"lineNumber":1,"position":2,"charType":"word","location":"12:87:2","textUthmani":"ٱذْهَبُوا۟","textQpcHafs":"ٱذۡهَبُواْ","textIndopak":"اذۡهَبُوۡا","codeV1":"ﭒ","codeV2":"ﱂ"},{"id":67050,"verseKey":"12:87","pageNumber":246,"lineNumber":1,"position":3,"charType":"word","location":"12:87:3","textUthmani":"فَتَحَسَّسُوا۟","textQpcHafs":"فَتَحَسَّسُواْ","textIndopak":"فَتَحَسَّسُوۡا","codeV1":"ﭓ","codeV2":"ﱃ"},{"id":67051,"verseKey":"12:87","pageNumber":246,"lineNumber":1,"position":4,"charType":"word","location":"12:87:4","textUthmani":"مِن","textQpcHafs":"مِن","textIndopak":"مِنۡ","codeV1":"ﭔ","codeV2":"ﱄ"},{"id":67052,"verseKey":"12:87","pageNumber":246,"lineNumber":1,"position":5,"charType":"word","location":"12:87:5","textUthmani":"يُوسُفَ","textQpcHafs":"يُوسُفَ","textIndopak":"يُّوۡسُفَ","codeV1":"ﭕ","codeV2":"ﱅ"},{"id":67053,"verseKey":"12:87","pageNumber":246,"lineNumber":1,"position":6,"charType":"word","location":"12:87:6","textUthmani":"وَأَخِيهِ","textQpcHafs":"وَأَخِيهِ","textIndopak":"وَاَخِيۡهِ","codeV1":"ﭖ","codeV2":"ﱆ"},{"id":67054,"verseKey":"12:87","pageNumber":246,"lineNumber":1,"position":7,"charType":"word","location":"12:87:7","textUthmani":"وَلَا","textQpcHafs":"وَلَا","textIndopak":"وَلَا","codeV1":"ﭗ","codeV2":"ﱇ"},{"id":67055,"verseKey":"12:87","pageNumber":246,"lineNumber":1,"position":8,"charType":"word","location":"12:87:8","textUthmani":"تَا۟يْـَٔسُوا۟","textQpcHafs":"تَاْيۡـَٔسُواْ","textIndopak":"تَايۡــَٔسُوۡا","codeV1":"ﭘ","codeV2":"ﱈ"},{"id":67056,"verseKey":"12:87","pageNumber":246,"lineNumber":2,"position":9,"charType":"word","location":"12:87:9","textUthmani":"مِن","textQpcHafs":"مِن","textIndopak":"مِنۡ","codeV1":"ﭙ","codeV2":"ﱉ"},{"id":67057,"verseKey":"12:87","pageNumber":246,"lineNumber":2,"position":10,"charType":"word","location":"12:87:10","textUthmani":"رَّوْحِ","textQpcHafs":"رَّوۡحِ","textIndopak":"رَّوۡحِ","codeV1":"ﭚ","codeV2":"ﱊ"},{"id":67058,"verseKey":"12:87","pageNumber":246,"lineNumber":2,"position":11,"charType":"word","location":"12:87:11","textUthmani":"ٱللَّهِ ۖ","textQpcHafs":"ٱللَّهِۖ","textIndopak":"اللّٰهِ​ؕ","codeV1":"ﭛﭜ","codeV2":"ﱋﱌ"},{"id":67060,"verseKey":"12:87","pageNumber":246,"lineNumber":2,"position":12,"charType":"word","location":"12:87:12","textUthmani":"إِنَّهُۥ","textQpcHafs":"إِنَّهُۥ","textIndopak":"اِنَّهٗ","codeV1":"ﭝ","codeV2":"ﱍ"},{"id":67061,"verseKey":"12:87","pageNumber":246,"lineNumber":2,"position":13,"charType":"word","location":"12:87:13","textUthmani":"لَا","textQpcHafs":"لَا","textIndopak":"لَا","codeV1":"ﭞ","codeV2":"ﱎ"},{"id":67062,"verseKey":"12:87","pageNumber":246,"lineNumber":2,"position":14,"charType":"word","location":"12:87:14","textUthmani":"يَا۟يْـَٔسُ","textQpcHafs":"يَاْيۡـَٔسُ","textIndopak":"يَايۡــَٔسُ","codeV1":"ﭟ","codeV2":"ﱏ"},{"id":67063,"verseKey":"12:87","pageNumber":246,"lineNumber":2,"position":15,"charType":"word","location":"12:87:15","textUthmani":"مِن","textQpcHafs":"مِن","textIndopak":"مِنۡ","codeV1":"ﭠ","codeV2":"ﱐ"},{"id":67064,"verseKey":"12:87","pageNumber":246,"lineNumber":2,"position":16,"charType":"word","location":"12:87:16","textUthmani":"رَّوْحِ","textQpcHafs":"رَّوۡحِ","textIndopak":"رَّوۡحِ","codeV1":"ﭡ","codeV2":"ﱑ"},{"id":67065,"verseKey":"12:87","pageNumber":246,"lineNumber":2,"position":17,"charType":"word","location":"12:87:17","textUthmani":"ٱللَّهِ","textQpcHafs":"ٱللَّهِ","textIndopak":"اللّٰهِ","codeV1":"ﭢ","codeV2":"ﱒ"},{"id":67066,"verseKey":"12:87","pageNumber":246,"lineNumber":2,"position":18,"charType":"word","location":"12:87:18","textUthmani":"إِلَّا","textQpcHafs":"إِلَّا","textIndopak":"اِلَّا","codeV1":"ﭣ","codeV2":"ﱓ"},{"id":67067,"verseKey":"12:87","pageNumber":246,"lineNumber":2,"position":19,"charType":"word","location":"12:87:19","textUthmani":"ٱلْقَوْمُ","textQpcHafs":"ٱلۡقَوۡمُ","textIndopak":"الۡقَوۡمُ","codeV1":"ﭤ","codeV2":"ﱔ"},{"id":67068,"verseKey":"12:87","pageNumber":246,"lineNumber":3,"position":20,"charType":"word","location":"12:87:20","textUthmani":"ٱلْكَـٰفِرُونَ","textQpcHafs":"ٱلۡكَٰفِرُونَ","textIndopak":"الۡكٰفِرُوۡنَ‏","codeV1":"ﭥ","codeV2":"ﱕ"},{"id":67069,"verseKey":"12:87","pageNumber":246,"lineNumber":3,"position":21,"charType":"end","location":"12:87:21","textUthmani":"٨٧","textQpcHafs":"٨٧","textIndopak":"٨٧","codeV1":"ﭦ","codeV2":"ﱖ"}]},{"id":1684,"verseKey":"12:88","chapterId":12,"pageNumber":246,"juzNumber":13,"hizbNumber":25,"rubElHizbNumber":98,"textUthmani":"فَلَمَّا دَخَلُوا۟ عَلَيْهِ قَالُوا۟ يَـٰٓأَيُّهَا ٱلْعَزِيزُ مَسَّنَا وَأَهْلَنَا ٱلضُّرُّ وَجِئْنَا بِبِضَـٰعَةٍ مُّزْجَىٰةٍ فَأَوْفِ لَنَا ٱلْكَيْلَ وَتَصَدَّقْ عَلَيْنَآ ۖ إِنَّ ٱللَّهَ يَجْزِى ٱلْمُتَصَدِّقِينَ","textIndopak":"فَلَمَّا دَخَلُوۡا عَلَيۡهِ قَالُوۡا يٰۤاَيُّهَا الۡعَزِيۡزُ مَسَّنَا وَاَهۡلَنَا الضُّرُّ وَجِئۡنَا بِبِضَاعَةٍ مُّزۡجٰٮةٍ فَاَوۡفِ لَنَا الۡكَيۡلَ وَتَصَدَّقۡ عَلَيۡنَاؕ اِنَّ اللّٰهَ يَجۡزِى الۡمُتَصَدِّقِيۡنَ‏","textUthmaniTajweed":"فَلَ<tajweed class=ghunnah>مّ</tajweed>َا دَخَلُو<tajweed class=slnt>اْ</tajweed> عَلَيْهِ قَالُو<tajweed class=slnt>اْ</tajweed> يَ<tajweed class=madda_obligatory>ـٰٓ</tajweed>أَيُّهَا <tajweed class=ham_wasl>ٱ</tajweed>لْعَزِيزُ مَسَّنَا وَأَهْلَنَا <tajweed class=ham_wasl>ٱ</tajweed><tajweed class=laam_shamsiyah>ل</tajweed>ضُّرُّ وَجِئْنَا بِبِضَ<tajweed class=madda_normal>ـٰ</tajweed>عَ<tajweed class=idgham_ghunnah>ةٍ م</tajweed>ُّزْجَ<tajweed class=madda_normal>ـٰ</tajweed><tajweed class=ikhafa>ةٍ ف</tajweed>َأَوْفِ لَنَا <tajweed class=ham_wasl>ٱ</tajweed>لْكَيْلَ وَتَصَدَّ<tajweed class=qalaqah>قْ</tajweed> عَلَيْن<tajweed class=madda_obligatory>َآ‌ۖ</tajweed> إِ<tajweed class=ghunnah>نّ</tajweed>َ <tajweed class=ham_wasl>ٱ</tajweed>للَّهَ يَ<tajweed class=qalaqah>جْ</tajweed>زِى <tajweed class=ham_wasl>ٱ</tajweed>لْمُتَصَدِّق<tajweed class=madda_permissible>ِي</tajweed>نَ <span class=end>٨٨</span>","words":[{"id":67341,"verseKey":"12:88","pageNumber":246,"lineNumber":3,"position":1,"charType":"word","location":"12:88:1","textUthmani":"فَلَمَّا","textQpcHafs":"فَلَمَّا","textIndopak":"فَلَمَّا","codeV1":"ﭧ","codeV2":"ﱗ"},{"id":67342,"verseKey":"12:88","pageNumber":246,"lineNumber":3,"position":2,"charType":"word","location":"12:88:2","textUthmani":"دَخَلُوا۟","textQpcHafs":"دَخَلُواْ","textIndopak":"دَخَلُوۡا","codeV1":"ﭨ","codeV2":"ﱘ"},{"id":67343,"verseKey":"12:88","pageNumber":246,"lineNumber":3,"position":3,"charType":"word","location":"12:88:3","textUthmani":"عَلَيْهِ","textQpcHafs":"عَلَيۡهِ","textIndopak":"عَلَيۡهِ","codeV1":"ﭩ","codeV2":"ﱙ"},{"id":67344,"verseKey":"12:88","pageNumber":246,"lineNumber":3,"position":4,"charType":"word","location":"12:88:4","textUthmani":"قَالُوا۟","textQpcHafs":"قَالُواْ","textIndopak":"قَالُوۡا","codeV1":"ﭪ","codeV2":"ﱚ"},{"id":67345,"verseKey":"12:88","pageNumber":246,"lineNumber":3,"position":5,"charType":"word","location":"12:88:5","textUthmani":"يَـٰٓأَيُّهَا","textQpcHafs":"يَٰٓأَيُّهَا","textIndopak":"يٰۤاَيُّهَا","codeV1":"ﭫ","codeV2":"ﱛ"},{"id":67346,"verseKey":"12:88","pageNumber":246,"lineNumber":3,"position":6,"charType":"word","location":"12:88:6","textUthmani":"ٱلْعَزِيزُ","textQpcHafs":"ٱلۡعَزِيزُ","textIndopak":"الۡعَزِيۡزُ","codeV1":"ﭬ","codeV2":"ﱜ"},{"id":67347,"verseKey":"12:88","pageNumber":246,"lineNumber":4,"position":7,"charType":"word","location":"12:88:7","textUthmani":"مَسَّنَا","textQpcHafs":"مَسَّنَا","textIndopak":"مَسَّنَا","codeV1":"ﭭ","codeV2":"ﱝ"},{"id":67348,"verseKey":"12:88","pageNumber":246,"lineNumber":4,"position":8,"charType":"word","location":"12:88:8","textUthmani":"وَأَهْلَنَا","textQpcHafs":"وَأَهۡلَنَا","textIndopak":"وَاَهۡلَنَا","codeV1":"ﭮ","codeV2":"ﱞ"},{"id":67349,"verseKey":"12:88","pageNumber":246,"lineNumber":4,"position":9,"charType":"word","location":"12:88:9","textUthmani":"ٱلضُّرُّ","textQpcHafs":"ٱلضُّرُّ","textIndopak":"الضُّرُّ","codeV1":"ﭯ","codeV2":"ﱟ"},{"id":67350,"verseKey":"12:88","pageNumber":246,"lineNumber":4,"position":10,"charType":"word","location":"12:88:10","textUthmani":"وَجِئْنَا","textQpcHafs":"وَجِئۡنَا","textIndopak":"وَجِئۡنَا","codeV1":"ﭰ","codeV2":"ﱠ"},{"id":67351,"verseKey":"12:88","pageNumber":246,"lineNumber":4,"position":11,"charType":"word","location":"12:88:11","textUthmani":"بِبِضَـٰعَةٍۢ","textQpcHafs":"بِبِضَٰعَةٖ","textIndopak":"بِبِضَاعَةٍ","codeV1":"ﭱ","codeV2":"ﱡ"},{"id":67352,"verseKey":"12:88","pageNumber":246,"lineNumber":4,"position":12,"charType":"word","location":"12:88:12","textUthmani":"مُّزْجَىٰةٍۢ","textQpcHafs":"مُّزۡجَىٰةٖ","textIndopak":"مُّزۡجٰٮةٍ","codeV1":"ﭲ","codeV2":"ﱢ"},{"id":67353,"verseKey":"12:88","pageNumber":246,"lineNumber":4,"position":13,"charType":"word","location":"12:88:13","textUthmani":"فَأَوْفِ","textQpcHafs":"فَأَوۡفِ","textIndopak":"فَاَوۡفِ","codeV1":"ﭳ","codeV2":"ﱣ"},{"id":67354,"verseKey":"12:88","pageNumber":246,"lineNumber":4,"position":14,"charType":"word","location":"12:88:14","textUthmani":"لَنَا","textQpcHafs":"لَنَا","textIndopak":"لَنَا","codeV1":"ﭴ","codeV2":"ﱤ"},{"id":67355,"verseKey":"12:88","pageNumber":246,"lineNumber":5,"position":15,"charType":"word","location":"12:88:15","textUthmani":"ٱلْكَيْلَ","textQpcHafs":"ٱلۡكَيۡلَ","textIndopak":"الۡكَيۡلَ","codeV1":"ﭵ","codeV2":"ﱥ"},{"id":67356,"verseKey":"12:88","pageNumber":246,"lineNumber":5,"position":16,"charType":"word","location":"12:88:16","textUthmani":"وَتَصَدَّقْ","textQpcHafs":"وَتَصَدَّقۡ","textIndopak":"وَتَصَدَّقۡ","codeV1":"ﭶ","codeV2":"ﱦ"},{"id":67357,"verseKey":"12:88","pageNumber":246,"lineNumber":5,"position":17,"charType":"word","location":"12:88:17","textUthmani":"عَلَيْنَآ ۖ","textQpcHafs":"عَلَيۡنَآۖ","textIndopak":"عَلَيۡنَاؕ","codeV1":"ﭷﭸ","codeV2":"ﱧﱨ"},{"id":67359,"verseKey":"12:88","pageNumber":246,"lineNumber":5,"position":18,"charType":"word","location":"12:88:18","textUthmani":"إِنَّ","textQpcHafs":"إِنَّ","textIndopak":"اِنَّ","codeV1":"ﭹ","codeV2":"ﱩ"},{"id":67360,"verseKey":"12:88","pageNumber":246,"lineNumber":5,"position":19,"charType":"word","location":"12:88:19","textUthmani":"ٱللَّهَ","textQpcHafs":"ٱللَّهَ","textIndopak":"اللّٰهَ","codeV1":"ﭺ","codeV2":"ﱪ"},{"id":67361,"verseKey":"12:88","pageNumber":246,"lineNumber":5,"position":20,"charType":"word","location":"12:88:20","textUthmani":"يَجْزِى","textQpcHafs":"يَجۡزِي","textIndopak":"يَجۡزِى","codeV1":"ﭻ","codeV2":"ﱫ"},{"id":67362,"verseKey":"12:88","pageNumber":246,"lineNumber":5,"position":21,"charType":"word","location":"12:88:21","textUthmani":"ٱلْمُتَصَدِّقِينَ","textQpcHafs":"ٱلۡمُتَصَدِّقِينَ","textIndopak":"الۡمُتَصَدِّقِيۡنَ‏","codeV1":"ﭼ","codeV2":"ﱬ"},{"id":67363,"verseKey":"12:88","pageNumber":246,"lineNumber":6,"position":22,"charType":"end","location":"12:88:22","textUthmani":"٨٨","textQpcHafs":"٨٨","textIndopak":"٨٨","codeV1":"ﭽ","codeV2":"ﱭ"}]},{"id":1685,"verseKey":"12:89","chapterId":12,"pageNumber":246,"juzNumber":13,"hizbNumber":25,"rubElHizbNumber":98,"textUthmani":"قَالَ هَلْ عَلِمْتُم مَّا فَعَلْتُم بِيُوسُفَ وَأَخِيهِ إِذْ أَنتُمْ جَـٰهِلُونَ","textIndopak":"قَالَ هَلۡ عَلِمۡتُمۡ مَّا فَعَلۡتُمۡ بِيُوۡسُفَ وَاَخِيۡهِ اِذۡ اَنۡتُمۡ جٰهِلُوۡنَ‏","textUthmaniTajweed":"قَالَ هَلْ عَلِمْت<tajweed class=idgham_shafawi>ُم م</tajweed>َّا فَعَلْت<tajweed class=ikhafa_shafawi>ُم ب</tajweed>ِيُوسُفَ وَأَخِيهِ إِذْ أَ<tajweed class=ikhafa>نت</tajweed>ُمْ جَ<tajweed class=madda_normal>ـٰ</tajweed>هِل<tajweed class=madda_permissible>ُو</tajweed>نَ <span class=end>٨٩</span>","words":[{"id":67835,"verseKey":"12:89","pageNumber":246,"lineNumber":6,"position":1,"charType":"word","location":"12:89:1","textUthmani":"قَالَ","textQpcHafs":"قَالَ","textIndopak":"قَالَ","codeV1":"ﭾ","codeV2":"ﱮ"},{"id":67836,"verseKey":"12:89","pageNumber":246,"lineNumber":6,"position":2,"charType":"word","location":"12:89:2","textUthmani":"هَلْ","textQpcHafs":"هَلۡ","textIndopak":"هَلۡ","codeV1":"ﭿ","codeV2":"ﱯ"},{"id":67837,"verseKey":"12:89","pageNumber":246,"lineNumber":6,"position":3,"charType":"word","location":"12:89:3","textUthmani":"عَلِمْتُم","textQpcHafs":"عَلِمۡتُم","textIndopak":"عَلِمۡتُمۡ","codeV1":"ﮀ","codeV2":"ﱰ"},{"id":67838,"verseKey":"12:89","pageNumber":246,"lineNumber":6,"position":4,"charType":"word","location":"12:89:4","textUthmani":"مَّا","textQpcHafs":"مَّا","textIndopak":"مَّا","codeV1":"ﮁ","codeV2":"ﱱ"},{"id":67839,"verseKey":"12:89","pageNumber":246,"lineNumber":6,"position":5,"charType":"word","location":"12:89:5","textUthmani":"فَعَلْتُم","textQpcHafs":"فَعَلۡتُم","textIndopak":"فَعَلۡتُمۡ","codeV1":"ﮂ","codeV2":"ﱲ"},{"id":67840,"verseKey":"12:89","pageNumber":246,"lineNumber":6,"position":6,"charType":"word","location":"12:89:6","textUthmani":"بِيُوسُفَ","textQpcHafs":"بِيُوسُفَ","textIndopak":"بِيُوۡسُفَ","codeV1":"ﮃ","codeV2":"ﱳ"},{"id":67841,"verseKey":"12:89","pageNumber":246,"lineNumber":6,"position":7,"charType":"word","location":"12:89:7","textUthmani":"وَأَخِيهِ","textQpcHafs":"وَأَخِيهِ","textIndopak":"وَاَخِيۡهِ","codeV1":"ﮄ","codeV2":"ﱴ"},{"id":67842,"verseKey":"12:89","pageNumber":246,"lineNumber":6,"position":8,"charType":"word","location":"12:89:8","textUthmani":"إِذْ","textQpcHafs":"إِذۡ","textIndopak":"اِذۡ","codeV1":"ﮅ","codeV2":"ﱵ"},{"id":67843,"verseKey":"12:89","pageNumber":246,"lineNumber":6,"position":9,"charType":"word","location":"12:89:9","textUthmani":"أَنتُمْ","textQpcHafs":"أَنتُمۡ","textIndopak":"اَنۡتُمۡ","codeV1":"ﮆ","codeV2":"ﱶ"},{"id":67844,"verseKey":"12:89","pageNumber":246,"lineNumber":7,"position":10,"charType":"word","location":"12:89:10","textUthmani":"جَـٰهِلُونَ","textQpcHafs":"جَٰهِلُونَ","textIndopak":"جٰهِلُوۡنَ‏","codeV1":"ﮇ","codeV2":"ﱷ"},{"id":67845,"verseKey":"12:89","pageNumber":246,"lineNumber":7,"position":11,"charType":"end","location":"12:89:11","textUthmani":"٨٩","textQpcHafs":"٨٩","textIndopak":"٨٩","codeV1":"ﮈ","codeV2":"ﱸ"}]},{"id":1686,"verseKey":"12:90","chapterId":12,"pageNumber":246,"juzNumber":13,"hizbNumber":25,"rubElHizbNumber":98,"textUthmani":"قَالُوٓا۟ أَءِنَّكَ لَأَنتَ يُوسُفُ ۖ قَالَ أَنَا۠ يُوسُفُ وَهَـٰذَآ أَخِى ۖ قَدْ مَنَّ ٱللَّهُ عَلَيْنَآ ۖ إِنَّهُۥ مَن يَتَّقِ وَيَصْبِرْ فَإِنَّ ٱللَّهَ لَا يُضِيعُ أَجْرَ ٱلْمُحْسِنِينَ","textIndopak":"قَالُوۡۤا ءَاِنَّكَ لَاَنۡتَ يُوۡسُفُ​ؕ قَالَ اَنَا يُوۡسُفُ وَهٰذَاۤ اَخِىۡ​ قَدۡ مَنَّ اللّٰهُ عَلَيۡنَاؕ اِنَّهٗ مَنۡ يَّتَّقِ وَيَصۡبِرۡ فَاِنَّ اللّٰهَ لَا يُضِيۡعُ اَجۡرَ الۡمُحۡسِنِيۡنَ‏","textUthmaniTajweed":"قَال<tajweed class=madda_obligatory>ُوٓ</tajweed><tajweed class=slnt>اْ</tajweed> أَءِ<tajweed class=ghunnah>نّ</tajweed>َكَ لَأَ<tajweed class=ikhafa>نت</tajweed>َ يُوسُفُ‌ۖ قَالَ أَنَا۟ يُوسُفُ وَهَ<tajweed class=madda_normal>ـٰ</tajweed>ذ<tajweed class=madda_obligatory>َآ</tajweed> أَخِى‌ۖ قَ<tajweed class=qalaqah>دْ</tajweed> مَ<tajweed class=ghunnah>نّ</tajweed>َ <tajweed class=ham_wasl>ٱ</tajweed>للَّهُ عَلَيْن<tajweed class=madda_obligatory>َآ‌ۖ</tajweed> إِ<tajweed class=ghunnah>نّ</tajweed>َهُ<tajweed class=madda_normal>ۥ</tajweed> م<tajweed class=idgham_ghunnah>َن ي</tajweed>َتَّقِ وَيَصْبِرْ فَإِ<tajweed class=ghunnah>نّ</tajweed>َ <tajweed class=ham_wasl>ٱ</tajweed>للَّهَ لَا يُضِيعُ أَ<tajweed class=qalaqah>جْ</tajweed>رَ <tajweed class=ham_wasl>ٱ</tajweed>لْمُحْسِن<tajweed class=madda_permissible>ِي</tajweed>نَ <span class=end>٩٠</span>","words":[{"id":68178,"verseKey":"12:90","pageNumber":246,"lineNumber":7,"position":1,"charType":"word","location":"12:90:1","textUthmani":"قَالُوٓا۟","textQpcHafs":"قَالُوٓاْ","textIndopak":"قَالُوۡۤا","codeV1":"ﮉ","codeV2":"ﱹ"},{"id":68179,"verseKey":"12:90","pageNumber":246,"lineNumber":7,"position":2,"charType":"word","location":"12:90:2","textUthmani":"أَءِنَّكَ","textQpcHafs":"أَءِنَّكَ","textIndopak":"ءَاِنَّكَ","codeV1":"ﮊ","codeV2":"ﱺ"},{"id":68180,"verseKey":"12:90","pageNumber":246,"lineNumber":7,"position":3,"charType":"word","location":"12:90:3","textUthmani":"لَأَنتَ","textQpcHafs":"لَأَنتَ","textIndopak":"لَاَنۡتَ","codeV1":"ﮋ","codeV2":"ﱻ"},{"id":68181,"verseKey":"12:90","pageNumber":246,"lineNumber":7,"position":4,"charType":"word","location":"12:90:4","textUthmani":"يُوسُفُ ۖ","textQpcHafs":"يُوسُفُۖ","textIndopak":"يُوۡسُفُ​ؕ","codeV1":"ﮌﮍ","codeV2":"ﱼﱽ"},{"id":68183,"verseKey":"12:90","pageNumber":246,"lineNumber":7,"position":5,"charType":"word","location":"12:90:5","textUthmani":"قَالَ","textQpcHafs":"قَالَ","textIndopak":"قَالَ","codeV1":"ﮎ","codeV2":"ﱾ"},{"id":68184,"verseKey":"12:90","pageNumber":246,"lineNumber":7,"position":6,"charType":"word","location":"12:90:6","textUthmani":"أَنَا۠","textQpcHafs":"أَنَا۠","textIndopak":"اَنَا","codeV1":"ﮏ","codeV2":"ﱿ"},{"id":68185,"verseKey":"12:90","pageNumber":246,"lineNumber":7,"position":7,"charType":"word","location":"12:90:7","textUthmani":"يُوسُفُ","textQpcHafs":"يُوسُفُ","textIndopak":"يُوۡسُفُ","codeV1":"ﮐ","codeV2":"ﲀ"},{"id":68186,"verseKey":"12:90","pageNumber":246,"lineNumber":8,"position":8,"charType":"word","location":"12:90:8","textUthmani":"وَهَـٰذَآ","textQpcHafs":"وَهَٰذَآ","textIndopak":"وَهٰذَاۤ","codeV1":"ﮑ","codeV2":"ﲁ"},{"id":68187,"verseKey":"12:90","pageNumber":246,"lineNumber":8,"position":9,"charType":"word","location":"12:90:9","textUthmani":"أَخِى ۖ","textQpcHafs":"أَخِيۖ","textIndopak":"اَخِىۡ​","codeV1":"ﮒﮓ","codeV2":"ﲂﲃ"},{"id":68189,"verseKey":"12:90","pageNumber":246,"lineNumber":8,"position":10,"charType":"word","location":"12:90:10","textUthmani":"قَدْ","textQpcHafs":"قَدۡ","textIndopak":"قَدۡ","codeV1":"ﮔ","codeV2":"ﲄ"},{"id":68190,"verseKey":"12:90","pageNumber":246,"lineNumber":8,"position":11,"charType":"word","location":"12:90:11","textUthmani":"مَنَّ","textQpcHafs":"مَنَّ","textIndopak":"مَنَّ","codeV1":"ﮕ","codeV2":"ﲅ"},{"id":68191,"verseKey":"12:90","pageNumber":246,"lineNumber":8,"position":12,"charType":"word","location":"12:90:12","textUthmani":"ٱللَّهُ","textQpcHafs":"ٱللَّهُ","textIndopak":"اللّٰهُ","codeV1":"ﮖ","codeV2":"ﲆ"},{"id":68192,"verseKey":"12:90","pageNumber":246,"lineNumber":8,"position":13,"charType":"word","location":"12:90:13","textUthmani":"عَلَيْنَآ ۖ","textQpcHafs":"عَلَيۡنَآۖ","textIndopak":"عَلَيۡنَاؕ","codeV1":"ﮗﮘ","codeV2":"ﲇﲈ"},{"id":68194,"verseKey":"12:90","pageNumber":246,"lineNumber":8,"position":14,"charType":"word","location":"12:90:14","textUthmani":"إِنَّهُۥ","textQpcHafs":"إِنَّهُۥ","textIndopak":"اِنَّهٗ","codeV1":"ﮙ","codeV2":"ﲉ"},{"id":68195,"verseKey":"12:90","pageNumber":246,"lineNumber":8,"position":15,"charType":"word","location":"12:90:15","textUthmani":"مَن","textQpcHafs":"مَن","textIndopak":"مَنۡ","codeV1":"ﮚ","codeV2":"ﲊ"},{"id":68196,"verseKey":"12:90","pageNumber":246,"lineNumber":8,"position":16,"charType":"word","location":"12:90:16","textUthmani":"يَتَّقِ","textQpcHafs":"يَتَّقِ","textIndopak":"يَّتَّقِ","codeV1":"ﮛ","codeV2":"ﲋ"},{"id":68197,"verseKey":"12:90","pageNumber":246,"lineNumber":8,"position":17,"charType":"word","location":"12:90:17","textUthmani":"وَيَصْبِرْ","textQpcHafs":"وَيَصۡبِرۡ","textIndopak":"وَيَصۡبِرۡ","codeV1":"ﮜ","codeV2":"ﲌ"},{"id":68198,"verseKey":"12:90","pageNumber":246,"lineNumber":8,"position":18,"charType":"word","location":"12:90:18","textUthmani":"فَإِنَّ","textQpcHafs":"فَإِنَّ","textIndopak":"فَاِنَّ","codeV1":"ﮝ","codeV2":"ﲍ"},{"id":68199,"verseKey":"12:90","pageNumber":246,"lineNumber":9,"position":19,"charType":"word","location":"12:90:19","textUthmani":"ٱللَّهَ","textQpcHafs":"ٱللَّهَ","textIndopak":"اللّٰهَ","codeV1":"ﮞ","codeV2":"ﲎ"},{"id":68200,"verseKey":"12:90","pageNumber":246,"lineNumber":9,"position":20,"charType":"word","location":"12:90:20","textUthmani":"لَا","textQpcHafs":"لَا","textIndopak":"لَا","codeV1":"ﮟ","codeV2":"ﲏ"},{"id":68201,"verseKey":"12:90","pageNumber":246,"lineNumber":9,"position":21,"charType":"word","location":"12:90:21","textUthmani":"يُضِيعُ","textQpcHafs":"يُضِيعُ","textIndopak":"يُضِيۡعُ","codeV1":"ﮠ","codeV2":"ﲐ"},{"id":68202,"verseKey":"12:90","pageNumber":246,"lineNumber":9,"position":22,"charType":"word","location":"12:90:22","textUthmani":"أَجْرَ","textQpcHafs":"أَجۡرَ","textIndopak":"اَجۡرَ","codeV1":"ﮡ","codeV2":"ﲑ"},{"id":68203,"verseKey":"12:90","pageNumber":246,"lineNumber":9,"position":23,"charType":"word","location":"12:90:23","textUthmani":"ٱلْمُحْسِنِينَ","textQpcHafs":"ٱلۡمُحۡسِنِينَ","textIndopak":"الۡمُحۡسِنِيۡنَ‏","codeV1":"ﮢ","codeV2":"ﲒ"},{"id":68204,"verseKey":"12:90","pageNumber":246,"lineNumber":9,"position":24,"charType":"end","location":"12:90:24","textUthmani":"٩٠","textQpcHafs":"٩٠","textIndopak":"٩٠","codeV1":"ﮣ","codeV2":"ﲓ"}]},{"id":1687,"verseKey":"12:91","chapterId":12,"pageNumber":246,"juzNumber":13,"hizbNumber":25,"rubElHizbNumber":98,"textUthmani":"قَالُوا۟ تَٱللَّهِ لَقَدْ ءَاثَرَكَ ٱللَّهُ عَلَيْنَا وَإِن كُنَّا لَخَـٰطِـِٔينَ","textIndopak":"قَالُوۡا تَاللّٰهِ لَقَدۡ اٰثَرَكَ اللّٰهُ عَلَيۡنَا وَاِنۡ كُنَّا لَخٰـطِــِٕيۡنَ‏ ﻿﻿","textUthmaniTajweed":"قَالُو<tajweed class=slnt>اْ</tajweed> تَ<tajweed class=ham_wasl>ٱ</tajweed>للَّهِ لَقَ<tajweed class=qalaqah>دْ</tajweed> ءَاثَرَكَ <tajweed class=ham_wasl>ٱ</tajweed>للَّهُ عَلَيْنَا وَإِ<tajweed class=ikhafa>ن ك</tajweed>ُ<tajweed class=ghunnah>نّ</tajweed>َا لَخَ<tajweed class=madda_normal>ـٰ</tajweed>طِــٔ<tajweed class=madda_permissible>ِي</tajweed>نَ <span class=end>٩١</span>","words":[{"id":68553,"verseKey":"12:91","pageNumber":246,"lineNumber":9,"position":1,"charType":"word","location":"12:91:1","textUthmani":"قَالُوا۟","textQpcHafs":"قَالُواْ","textIndopak":"قَالُوۡا","codeV1":"ﮤ","codeV2":"ﲔ"},{"id":68554,"verseKey":"12:91","pageNumber":246,"lineNumber":9,"position":2,"charType":"word","location":"12:91:2","textUthmani":"تَٱللَّهِ","textQpcHafs":"تَٱللَّهِ","textIndopak":"تَاللّٰهِ","codeV1":"ﮥ","codeV2":"ﲕ"},{"id":68555,"verseKey":"12:91","pageNumber":246,"lineNumber":9,"position":3,"charType":"word","location":"12:91:3","textUthmani":"لَقَدْ","textQpcHafs":"لَقَدۡ","textIndopak":"لَقَدۡ","codeV1":"ﮦ","codeV2":"ﲖ"},{"id":68556,"verseKey":"12:91","pageNumber":246,"lineNumber":10,"position":4,"charType":"word","location":"12:91:4","textUthmani":"ءَاثَرَكَ","textQpcHafs":"ءَاثَرَكَ","textIndopak":"اٰثَرَكَ","codeV1":"ﮧ","codeV2":"ﲗ"},{"id":68557,"verseKey":"12:91","pageNumber":246,"lineNumber":10,"position":5,"charType":"word","location":"12:91:5","textUthmani":"ٱللَّهُ","textQpcHafs":"ٱللَّهُ","textIndopak":"اللّٰهُ","codeV1":"ﮨ","codeV2":"ﲘ"},{"id":68558,"verseKey":"12:91","pageNumber":246,"lineNumber":10,"position":6,"charType":"word","location":"12:91:6","textUthmani":"عَلَيْنَا","textQpcHafs":"عَلَيۡنَا","textIndopak":"عَلَيۡنَا","codeV1":"ﮩ","codeV2":"ﲙ"},{"id":68559,"verseKey":"12:91","pageNumber":246,"lineNumber":10,"position":7,"charType":"word","location":"12:91:7","textUthmani":"وَإِن","textQpcHafs":"وَإِن","textIndopak":"وَاِنۡ","codeV1":"ﮪ","codeV2":"ﲚ"},{"id":68560,"verseKey":"12:91","pageNumber":246,"lineNumber":10,"position":8,"charType":"word","location":"12:91:8","textUthmani":"كُنَّا","textQpcHafs":"كُنَّا","textIndopak":"كُنَّا","codeV1":"ﮫ","codeV2":"ﲛ"},{"id":68561,"verseKey":"12:91","pageNumber":246,"lineNumber":10,"position":9,"charType":"word","location":"12:91:9","textUthmani":"لَخَـٰطِـِٔينَ","textQpcHafs":"لَخَٰطِـِٔينَ","textIndopak":"لَخٰـطِــِٕيۡنَ‏ ﻿﻿","codeV1":"ﮬ","codeV2":"ﲜ"},{"id":68562,"verseKey":"12:91","pageNumber":246,"lineNumber":10,"position":10,"charType":"end","location":"12:91:10","textUthmani":"٩١","textQpcHafs":"٩١","textIndopak":"٩١","codeV1":"ﮭ","codeV2":"ﲝ"}]},{"id":1688,"verseKey":"12:92","chapterId":12,"pageNumber":246,"juzNumber":13,"hizbNumber":25,"rubElHizbNumber":98,"textUthmani":"قَالَ لَا تَثْرِيبَ عَلَيْكُمُ ٱلْيَوْمَ ۖ يَغْفِرُ ٱللَّهُ لَكُمْ ۖ وَهُوَ أَرْحَمُ ٱلرَّٰحِمِينَ","textIndopak":"قَالَ لَا تَثۡرِيۡبَ عَلَيۡكُمُ الۡيَوۡمَ​ؕ يَغۡفِرُ اللّٰهُ لَـكُمۡ​ وَهُوَ اَرۡحَمُ الرّٰحِمِيۡنَ‏","textUthmaniTajweed":"قَالَ لَا تَثْرِيبَ عَلَيْكُمُ <tajweed class=ham_wasl>ٱ</tajweed>لْيَوْمَ‌ۖ يَغْفِرُ <tajweed class=ham_wasl>ٱ</tajweed>للَّهُ لَكُمْ‌ۖ وَهُوَ أَرْحَمُ <tajweed class=ham_wasl>ٱ</tajweed><tajweed class=laam_shamsiyah>ل</tajweed>رّ<tajweed class=madda_normal>َٲ</tajweed>حِم<tajweed class=madda_permissible>ِي</tajweed>نَ <span class=end>٩٢</span>","words":[{"id":68592,"verseKey":"12:92","pageNumber":246,"lineNumber":10,"position":1,"charType":"word","location":"12:92:1","textUthmani":"قَالَ","textQpcHafs":"قَالَ","textIndopak":"قَالَ","codeV1":"ﮮ","codeV2":"ﲞ"},{"id":68593,"verseKey":"12:92","pageNumber":246,"lineNumber":10,"position":2,"charType":"word","location":"12:92:2","textUthmani":"لَا","textQpcHafs":"لَا","textIndopak":"لَا","codeV1":"ﮯ","codeV2":"ﲟ"},{"id":68594,"verseKey":"12:92","pageNumber":246,"lineNumber":10,"position":3,"charType":"word","location":"12:92:3","textUthmani":"تَثْرِيبَ","textQpcHafs":"تَثۡرِيبَ","textIndopak":"تَثۡرِيۡبَ","codeV1":"ﮰ","codeV2":"ﲠ"},{"id":68595,"verseKey":"12:92","pageNumber":246,"lineNumber":11,"position":4,"charType":"word","location":"12:92:4","textUthmani":"عَلَيْكُمُ","textQpcHafs":"عَلَيۡكُمُ","textIndopak":"عَلَيۡكُمُ","codeV1":"ﮱ","codeV2":"ﲡ"},{"id":68596,"verseKey":"12:92","pageNumber":246,"lineNumber":11,"position":5,"charType":"word","location":"12:92:5","textUthmani":"ٱلْيَوْمَ ۖ","textQpcHafs":"ٱلۡيَوۡمَۖ","textIndopak":"الۡيَوۡمَ​ؕ","codeV1":"ﯓﯔ","codeV2":"ﲢﲣ"},{"id":68598,"verseKey":"12:92","pageNumber":246,"lineNumber":11,"position":6,"charType":"word","location":"12:92:6","textUthmani":"يَغْفِرُ","textQpcHafs":"يَغۡفِرُ","textIndopak":"يَغۡفِرُ","codeV1":"ﯕ","codeV2":"ﲤ"},{"id":68599,"verseKey":"12:92","pageNumber":246,"lineNumber":11,"position":7,"charType":"word","location":"12:92:7","textUthmani":"ٱللَّهُ","textQpcHafs":"ٱللَّهُ","textIndopak":"اللّٰهُ","codeV1":"ﯖ","codeV2":"ﲥ"},{"id":68600,"verseKey":"12:92","pageNumber":246,"lineNumber":11,"position":8,"charType":"word","location":"12:92:8","textUthmani":"لَكُمْ ۖ","textQpcHafs":"لَكُمۡۖ","textIndopak":"لَـكُمۡ​","codeV1":"ﯗﯘ","codeV2":"ﲦﲧ"},{"id":68602,"verseKey":"12:92","pageNumber":246,"lineNumber":11,"position":9,"charType":"word","location":"12:92:9","textUthmani":"وَهُوَ","textQpcHafs":"وَهُوَ","textIndopak":"وَهُوَ","codeV1":"ﯙ","codeV2":"ﲨ"},{"id":68603,"verseKey":"12:92","pageNumber":246,"lineNumber":11,"position":10,"charType":"word","location":"12:92:10","textUthmani":"أَرْحَمُ","textQpcHafs":"أَرۡحَمُ","textIndopak":"اَرۡحَمُ","codeV1":"ﯚ","codeV2":"ﲩ"},{"id":68604,"verseKey":"12:92","pageNumber":246,"lineNumber":11,"position":11,"charType":"word","location":"12:92:11","textUthmani":"ٱلرَّٰحِمِينَ","textQpcHafs":"ٱلرَّٰحِمِينَ","textIndopak":"الرّٰحِمِيۡنَ‏","codeV1":"ﯛ","codeV2":"ﲪ"},{"id":68605,"verseKey":"12:92","pageNumber":246,"lineNumber":12,"position":12,"charType":"end","location":"12:92:12","textUthmani":"٩٢","textQpcHafs":"٩٢","textIndopak":"٩٢","codeV1":"ﯜ","codeV2":"ﲫ"}]},{"id":1689,"verseKey":"12:93","chapterId":12,"pageNumber":246,"juzNumber":13,"hizbNumber":25,"rubElHizbNumber":98,"textUthmani":"ٱذْهَبُوا۟ بِقَمِيصِى هَـٰذَا فَأَلْقُوهُ عَلَىٰ وَجْهِ أَبِى يَأْتِ بَصِيرًا وَأْتُونِى بِأَهْلِكُمْ أَجْمَعِينَ","textIndopak":"اِذۡهَبُوۡا بِقَمِيۡصِىۡ هٰذَا فَاَلۡقُوۡهُ عَلٰى وَجۡهِ اَبِىۡ يَاۡتِ بَصِيۡرًا​ۚ وَاۡتُوۡنِىۡ بِاَهۡلِكُمۡ اَجۡمَعِيۡنَ‏","textUthmaniTajweed":"ٱذْهَبُو<tajweed class=slnt>اْ</tajweed> بِقَمِيصِى هَ<tajweed class=madda_normal>ـٰ</tajweed>ذَا فَأَلْقُوهُ عَلَىٰ وَ<tajweed class=qalaqah>جْ</tajweed>هِ أَبِى يَأْتِ بَصِي<tajweed class=idgham_ghunnah>رًا و</tajweed>َأْتُونِى بِأَهْلِكُمْ أَ<tajweed class=qalaqah>جْ</tajweed>مَع<tajweed class=madda_permissible>ِي</tajweed>نَ <span class=end>٩٣</span>","words":[{"id":69281,"verseKey":"12:93","pageNumber":246,"lineNumber":12,"position":1,"charType":"word","location":"12:93:1","textUthmani":"ٱذْهَبُوا۟","textQpcHafs":"ٱذۡهَبُواْ","textIndopak":"اِذۡهَبُوۡا","codeV1":"ﯝ","codeV2":"ﲬ"},{"id":69282,"verseKey":"12:93","pageNumber":246,"lineNumber":12,"position":2,"charType":"word","location":"12:93:2","textUthmani":"بِقَمِيصِى","textQpcHafs":"بِقَمِيصِي","textIndopak":"بِقَمِيۡصِىۡ","codeV1":"ﯞ","codeV2":"ﲭ"},{"id":69283,"verseKey":"12:93","pageNumber":246,"lineNumber":12,"position":3,"charType":"word","location":"12:93:3","textUthmani":"هَـٰذَا","textQpcHafs":"هَٰذَا","textIndopak":"هٰذَا","codeV1":"ﯟ","codeV2":"ﲮ"},{"id":69284,"verseKey":"12:93","pageNumber":246,"lineNumber":12,"position":4,"charType":"word","location":"12:93:4","textUthmani":"فَأَلْقُوهُ","textQpcHafs":"فَأَلۡقُوهُ","textIndopak":"فَاَلۡقُوۡهُ","codeV1":"ﯠ","codeV2":"ﲯ"},{"id":69285,"verseKey":"12:93","pageNumber":246,"lineNumber":12,"position":5,"charType":"word","location":"12:93:5","textUthmani":"عَلَىٰ","textQpcHafs":"عَلَىٰ","textIndopak":"عَلٰى","codeV1":"ﯡ","codeV2":"ﲰ"},{"id":69286,"verseKey":"12:93","pageNumber":246,"lineNumber":12,"position":6,"charType":"word","location":"12:93:6","textUthmani":"وَجْهِ","textQpcHafs":"وَجۡهِ","textIndopak":"وَجۡهِ","codeV1":"ﯢ","codeV2":"ﲱ"},{"id":69287,"verseKey":"12:93","pageNumber":246,"lineNumber":12,"position":7,"charType":"word","location":"12:93:7","textUthmani":"أَبِى","textQpcHafs":"أَبِي","textIndopak":"اَبِىۡ","codeV1":"ﯣ","codeV2":"ﲲ"},{"id":69288,"verseKey":"12:93","pageNumber":246,"lineNumber":12,"position":8,"charType":"word","location":"12:93:8","textUthmani":"يَأْتِ","textQpcHafs":"يَأۡتِ","textIndopak":"يَاۡتِ","codeV1":"ﯤ","codeV2":"ﲳ"},{"id":69289,"verseKey":"12:93","pageNumber":246,"lineNumber":13,"position":9,"charType":"word","location":"12:93:9","textUthmani":"بَصِيرًۭا","textQpcHafs":"بَصِيرٗا","textIndopak":"بَصِيۡرًا​ۚ","codeV1":"ﯥ","codeV2":"ﲴ"},{"id":69290,"verseKey":"12:93","pageNumber":246,"lineNumber":13,"position":10,"charType":"word","location":"12:93:10","textUthmani":"وَأْتُونِى","textQpcHafs":"وَأۡتُونِي","textIndopak":"وَاۡتُوۡنِىۡ","codeV1":"ﯦ","codeV2":"ﲵ"},{"id":69291,"verseKey":"12:93","pageNumber":246,"lineNumber":13,"position":11,"charType":"word","location":"12:93:11","textUthmani":"بِأَهْلِكُمْ","textQpcHafs":"بِأَهۡلِكُمۡ","textIndopak":"بِاَهۡلِكُمۡ","codeV1":"ﯧ","codeV2":"ﲶ"},{"id":69292,"verseKey":"12:93","pageNumber":246,"lineNumber":13,"position":12,"charType":"word","location":"12:93:12","textUthmani":"أَجْمَعِينَ","textQpcHafs":"أَجۡمَعِينَ","textIndopak":"اَجۡمَعِيۡنَ‏","codeV1":"ﯨ","codeV2":"ﲷ"},{"id":69293,"verseKey":"12:93","pageNumber":246,"lineNumber":13,"position":13,"charType":"end","location":"12:93:13","textUthmani":"٩٣","textQpcHafs":"٩٣","textIndopak":"٩٣","codeV1":"ﯩ","codeV2":"ﲸ"}]},{"id":1690,"verseKey":"12:94","chapterId":12,"pageNumber":246,"juzNumber":13,"hizbNumber":25,"rubElHizbNumber":98,"textUthmani":"وَلَمَّا فَصَلَتِ ٱلْعِيرُ قَالَ أَبُوهُمْ إِنِّى لَأَجِدُ رِيحَ يُوسُفَ ۖ لَوْلَآ أَن تُفَنِّدُونِ","textIndopak":"وَلَمَّا فَصَلَتِ الۡعِيۡرُ قَالَ اَبُوۡهُمۡ اِنِّىۡ لَاَجِدُ رِيۡحَ يُوۡسُفَ​ لَوۡلَاۤ اَنۡ تُفَـنِّدُوۡنِ‏","textUthmaniTajweed":"وَلَ<tajweed class=ghunnah>مّ</tajweed>َا فَصَلَتِ <tajweed class=ham_wasl>ٱ</tajweed>لْعِيرُ قَالَ أَبُوهُمْ إِ<tajweed class=ghunnah>نّ</tajweed>ِى لَأَجِدُ رِيحَ يُوسُفَ‌ۖ لَوْل<tajweed class=madda_obligatory>َآ</tajweed> أَ<tajweed class=ikhafa>ن ت</tajweed>ُفَ<tajweed class=ghunnah>نّ</tajweed>ِد<tajweed class=madda_permissible>ُو</tajweed>نِ <span class=end>٩٤</span>","words":[{"id":69622,"verseKey":"12:94","pageNumber":246,"lineNumber":13,"position":1,"charType":"word","location":"12:94:1","textUthmani":"وَلَمَّا","textQpcHafs":"وَلَمَّا","textIndopak":"وَلَمَّا","codeV1":"ﯪ","codeV2":"ﲹ"},{"id":69623,"verseKey":"12:94","pageNumber":246,"lineNumber":13,"position":2,"charType":"word","location":"12:94:2","textUthmani":"فَصَلَتِ","textQpcHafs":"فَصَلَتِ","textIndopak":"فَصَلَتِ","codeV1":"ﯫ","codeV2":"ﲺ"},{"id":69624,"verseKey":"12:94","pageNumber":246,"lineNumber":14,"position":3,"charType":"word","location":"12:94:3","textUthmani":"ٱلْعِيرُ","textQpcHafs":"ٱلۡعِيرُ","textIndopak":"الۡعِيۡرُ","codeV1":"ﯬ","codeV2":"ﲻ"},{"id":69625,"verseKey":"12:94","pageNumber":246,"lineNumber":14,"position":4,"charType":"word","location":"12:94:4","textUthmani":"قَالَ","textQpcHafs":"قَالَ","textIndopak":"قَالَ","codeV1":"ﯭ","codeV2":"ﲼ"},{"id":69626,"verseKey":"12:94","pageNumber":246,"lineNumber":14,"position":5,"charType":"word","location":"12:94:5","textUthmani":"أَبُوهُمْ","textQpcHafs":"أَبُوهُمۡ","textIndopak":"اَبُوۡهُمۡ","codeV1":"ﯮ","codeV2":"ﲽ"},{"id":69627,"verseKey":"12:94","pageNumber":246,"lineNumber":14,"position":6,"charType":"word","location":"12:94:6","textUthmani":"إِنِّى","textQpcHafs":"إِنِّي","textIndopak":"اِنِّىۡ","codeV1":"ﯯ","codeV2":"ﲾ"},{"id":69628,"verseKey":"12:94","pageNumber":246,"lineNumber":14,"position":7,"charType":"word","location":"12:94:7","textUthmani":"لَأَجِدُ","textQpcHafs":"لَأَجِدُ","textIndopak":"لَاَجِدُ","codeV1":"ﯰ","codeV2":"ﲿ"},{"id":69629,"verseKey":"12:94","pageNumber":246,"lineNumber":14,"position":8,"charType":"word","location":"12:94:8","textUthmani":"رِيحَ","textQpcHafs":"رِيحَ","textIndopak":"رِيۡحَ","codeV1":"ﯱ","codeV2":"ﳀ"},{"id":69630,"verseKey":"12:94","pageNumber":246,"lineNumber":14,"position":9,"charType":"word","location":"12:94:9","textUthmani":"يُوسُفَ ۖ","textQpcHafs":"يُوسُفَۖ","textIndopak":"يُوۡسُفَ​","codeV1":"ﯲﯳ","codeV2":"ﳁﳂ"},{"id":69632,"verseKey":"12:94","pageNumber":246,"lineNumber":14,"position":10,"charType":"word","location":"12:94:10","textUthmani":"لَوْلَآ","textQpcHafs":"لَوۡلَآ","textIndopak":"لَوۡلَاۤ","codeV1":"ﯴ","codeV2":"ﳃ"},{"id":69633,"verseKey":"12:94","pageNumber":246,"lineNumber":14,"position":11,"charType":"word","location":"12:94:11","textUthmani":"أَن","textQpcHafs":"أَن","textIndopak":"اَنۡ","codeV1":"ﯵ","codeV2":"ﳄ"},{"id":69634,"verseKey":"12:94","pageNumber":246,"lineNumber":15,"position":12,"charType":"word","location":"12:94:12","textUthmani":"تُفَنِّدُونِ","textQpcHafs":"تُفَنِّدُونِ","textIndopak":"تُفَـنِّدُوۡنِ‏","codeV1":"ﯶ","codeV2":"ﳅ"},{"id":69635,"verseKey":"12:94","pageNumber":246,"lineNumber":15,"position":13,"charType":"end","location":"12:94:13","textUthmani":"٩٤","textQpcHafs":"٩٤","textIndopak":"٩٤","codeV1":"ﯷ","codeV2":"ﳆ"}]},{"id":1691,"verseKey":"12:95","chapterId":12,"pageNumber":246,"juzNumber":13,"hizbNumber":25,"rubElHizbNumber":98,"textUthmani":"قَالُوا۟ تَٱللَّهِ إِنَّكَ لَفِى ضَلَـٰلِكَ ٱلْقَدِيمِ","textIndopak":"قَالُوۡا تَاللّٰهِ اِنَّكَ لَفِىۡ ضَلٰلِكَ الۡقَدِيۡمِ‏","textUthmaniTajweed":"قَالُو<tajweed class=slnt>اْ</tajweed> تَ<tajweed class=ham_wasl>ٱ</tajweed>للَّهِ إِ<tajweed class=ghunnah>نّ</tajweed>َكَ لَفِى ضَلَ<tajweed class=madda_normal>ـٰ</tajweed>لِكَ <tajweed class=ham_wasl>ٱ</tajweed>لْقَد<tajweed class=madda_permissible>ِي</tajweed>مِ <span class=end>٩٥</span>","words":[{"id":69928,"verseKey":"12:95","pageNumber":246,"lineNumber":15,"position":1,"charType":"word","location":"12:95:1","textUthmani":"قَالُوا۟","textQpcHafs":"قَالُواْ","textIndopak":"قَالُوۡا","codeV1":"ﯸ","codeV2":"ﳇ"},{"id":69929,"verseKey":"12:95","pageNumber":246,"lineNumber":15,"position":2,"charType":"word","location":"12:95:2","textUthmani":"تَٱللَّهِ","textQpcHafs":"تَٱللَّهِ","textIndopak":"تَاللّٰهِ","codeV1":"ﯹ","codeV2":"ﳈ"},{"id":69930,"verseKey":"12:95","pageNumber":246,"lineNumber":15,"position":3,"charType":"word","location":"12:95:3","textUthmani":"إِنَّكَ","textQpcHafs":"إِنَّكَ","textIndopak":"اِنَّكَ","codeV1":"ﯺ","codeV2":"ﳉ"},{"id":69931,"verseKey":"12:95","pageNumber":246,"lineNumber":15,"position":4,"charType":"word","location":"12:95:4","textUthmani":"لَفِى","textQpcHafs":"لَفِي","textIndopak":"لَفِىۡ","codeV1":"ﯻ","codeV2":"ﳊ"},{"id":69932,"verseKey":"12:95","pageNumber":246,"lineNumber":15,"position":5,"charType":"word","location":"12:95:5","textUthmani":"ضَلَـٰلِكَ","textQpcHafs":"ضَلَٰلِكَ","textIndopak":"ضَلٰلِكَ","codeV1":"ﯼ","codeV2":"ﳋ"},{"id":69933,"verseKey":"12:95","pageNumber":246,"lineNumber":15,"position":6,"charType":"word","location":"12:95:6","textUthmani":"ٱلْقَدِيمِ","textQpcHafs":"ٱلۡقَدِيمِ","textIndopak":"الۡقَدِيۡمِ‏","codeV1":"ﯽ","codeV2":"ﳌ"},{"id":69934,"verseKey":"12:95","pageNumber":246,"lineNumber":15,"position":7,"charType":"end","location":"12:95:7","textUthmani":"٩٥","textQpcHafs":"٩٥","textIndopak":"٩٥","codeV1":"ﯾ","codeV2":"ﳍ"}]}]}