{"packId":"qcf-madani-v1","version":"v1","pageNumber":141,"verses":[{"id":891,"verseKey":"6:102","chapterId":6,"pageNumber":141,"juzNumber":7,"hizbNumber":14,"rubElHizbNumber":56,"textUthmani":"ذَٰلِكُمُ ٱللَّهُ رَبُّكُمْ ۖ لَآ إِلَـٰهَ إِلَّا هُوَ ۖ خَـٰلِقُ كُلِّ شَىْءٍ فَٱعْبُدُوهُ ۚ وَهُوَ عَلَىٰ كُلِّ شَىْءٍ وَكِيلٌ","textIndopak":"ذٰ لِكُمُ اللّٰهُ رَبُّكُمۡ​ۚ لَاۤ اِلٰهَ اِلَّا هُوَ​ۚ خَالِقُ كُلِّ شَىۡءٍ فَاعۡبُدُوۡهُ​ۚ وَهُوَ عَلٰى كُلِّ شَىۡءٍ وَّكِيۡلٌ‏","textUthmaniTajweed":"ذ<tajweed class=madda_normal>َٲ</tajweed>لِكُمُ <tajweed class=ham_wasl>ٱ</tajweed>للَّهُ رَبُّكُمْ‌ۖ ل<tajweed class=madda_obligatory>َآ</tajweed> إِلَ<tajweed class=madda_normal>ـٰ</tajweed>هَ إِلَّا هُوَ‌ۖ خَ<tajweed class=madda_normal>ـٰ</tajweed>لِقُ كُلِّ ش<tajweed class=ikhafa>َىْءٍ ف</tajweed>َ<tajweed class=ham_wasl>ٱ</tajweed>عْبُدُوهُ‌ۚ وَهُوَ عَلَىٰ كُلِّ ش<tajweed class=idgham_ghunnah>َىْءٍ و</tajweed>َك<tajweed class=madda_permissible>ِي</tajweed>لٌ <span class=end>١٠٢</span>","words":[{"id":72006,"verseKey":"6:102","pageNumber":141,"lineNumber":1,"position":1,"charType":"word","location":"6:102:1","textUthmani":"ذَٰلِكُمُ","textQpcHafs":"ذَٰلِكُمُ","textIndopak":"ذٰ لِكُمُ","codeV1":"ﭑ","codeV2":"ﱁ"},{"id":72007,"verseKey":"6:102","pageNumber":141,"lineNumber":1,"position":2,"charType":"word","location":"6:102:2","textUthmani":"ٱللَّهُ","textQpcHafs":"ٱللَّهُ","textIndopak":"اللّٰهُ","codeV1":"ﭒ","codeV2":"ﱂ"},{"id":72008,"verseKey":"6:102","pageNumber":141,"lineNumber":1,"position":3,"charType":"word","location":"6:102:3","textUthmani":"رَبُّكُمْ ۖ","textQpcHafs":"رَبُّكُمۡۖ","textIndopak":"رَبُّكُمۡ​ۚ","codeV1":"ﭓﭔ","codeV2":"ﱃﱄ"},{"id":72010,"verseKey":"6:102","pageNumber":141,"lineNumber":1,"position":4,"charType":"word","location":"6:102:4","textUthmani":"لَآ","textQpcHafs":"لَآ","textIndopak":"لَاۤ","codeV1":"ﭕ","codeV2":"ﱅ"},{"id":72011,"verseKey":"6:102","pageNumber":141,"lineNumber":1,"position":5,"charType":"word","location":"6:102:5","textUthmani":"إِلَـٰهَ","textQpcHafs":"إِلَٰهَ","textIndopak":"اِلٰهَ","codeV1":"ﭖ","codeV2":"ﱆ"},{"id":72012,"verseKey":"6:102","pageNumber":141,"lineNumber":1,"position":6,"charType":"word","location":"6:102:6","textUthmani":"إِلَّا","textQpcHafs":"إِلَّا","textIndopak":"اِلَّا","codeV1":"ﭗ","codeV2":"ﱇ"},{"id":72013,"verseKey":"6:102","pageNumber":141,"lineNumber":1,"position":7,"charType":"word","location":"6:102:7","textUthmani":"هُوَ ۖ","textQpcHafs":"هُوَۖ","textIndopak":"هُوَ​ۚ","codeV1":"ﭘﭙ","codeV2":"ﱈﱉ"},{"id":72015,"verseKey":"6:102","pageNumber":141,"lineNumber":1,"position":8,"charType":"word","location":"6:102:8","textUthmani":"خَـٰلِقُ","textQpcHafs":"خَٰلِقُ","textIndopak":"خَالِقُ","codeV1":"ﭚ","codeV2":"ﱊ"},{"id":72016,"verseKey":"6:102","pageNumber":141,"lineNumber":1,"position":9,"charType":"word","location":"6:102:9","textUthmani":"كُلِّ","textQpcHafs":"كُلِّ","textIndopak":"كُلِّ","codeV1":"ﭛ","codeV2":"ﱋ"},{"id":72017,"verseKey":"6:102","pageNumber":141,"lineNumber":1,"position":10,"charType":"word","location":"6:102:10","textUthmani":"شَىْءٍۢ","textQpcHafs":"شَيۡءٖ","textIndopak":"شَىۡءٍ","codeV1":"ﭜ","codeV2":"ﱌ"},{"id":72018,"verseKey":"6:102","pageNumber":141,"lineNumber":1,"position":11,"charType":"word","location":"6:102:11","textUthmani":"فَٱعْبُدُوهُ ۚ","textQpcHafs":"فَٱعۡبُدُوهُۚ","textIndopak":"فَاعۡبُدُوۡهُ​ۚ","codeV1":"ﭝﭞ","codeV2":"ﱍﱎ"},{"id":72020,"verseKey":"6:102","pageNumber":141,"lineNumber":2,"position":12,"charType":"word","location":"6:102:12","textUthmani":"وَهُوَ","textQpcHafs":"وَهُوَ","textIndopak":"وَهُوَ","codeV1":"ﭟ","codeV2":"ﱏ"},{"id":72021,"verseKey":"6:102","pageNumber":141,"lineNumber":2,"position":13,"charType":"word","location":"6:102:13","textUthmani":"عَلَىٰ","textQpcHafs":"عَلَىٰ","textIndopak":"عَلٰى","codeV1":"ﭠ","codeV2":"ﱐ"},{"id":72022,"verseKey":"6:102","pageNumber":141,"lineNumber":2,"position":14,"charType":"word","location":"6:102:14","textUthmani":"كُلِّ","textQpcHafs":"كُلِّ","textIndopak":"كُلِّ","codeV1":"ﭡ","codeV2":"ﱑ"},{"id":72023,"verseKey":"6:102","pageNumber":141,"lineNumber":2,"position":15,"charType":"word","location":"6:102:15","textUthmani":"شَىْءٍۢ","textQpcHafs":"شَيۡءٖ","textIndopak":"شَىۡءٍ","codeV1":"ﭢ","codeV2":"ﱒ"},{"id":72024,"verseKey":"6:102","pageNumber":141,"lineNumber":2,"position":16,"charType":"word","location":"6:102:16","textUthmani":"وَكِيلٌۭ","textQpcHafs":"وَكِيلٞ","textIndopak":"وَّكِيۡلٌ‏","codeV1":"ﭣ","codeV2":"ﱓ"},{"id":72025,"verseKey":"6:102","pageNumber":141,"lineNumber":2,"position":17,"charType":"end","location":"6:102:17","textUthmani":"١٠٢","textQpcHafs":"١٠٢","textIndopak":"١٠٢","codeV1":"ﭤ","codeV2":"ﱔ"}]},{"id":892,"verseKey":"6:103","chapterId":6,"pageNumber":141,"juzNumber":7,"hizbNumber":14,"rubElHizbNumber":56,"textUthmani":"لَّا تُدْرِكُهُ ٱلْأَبْصَـٰرُ وَهُوَ يُدْرِكُ ٱلْأَبْصَـٰرَ ۖ وَهُوَ ٱللَّطِيفُ ٱلْخَبِيرُ","textIndopak":"لَا تُدۡرِكُهُ الۡاَبۡصَارُ وَهُوَ يُدۡرِكُ الۡاَبۡصَارَ​ۚ وَهُوَ اللَّطِيۡفُ الۡخَبِيۡرُ‏","textUthmaniTajweed":"لَّا تُ<tajweed class=qalaqah>دْ</tajweed>رِكُهُ <tajweed class=ham_wasl>ٱ</tajweed>لْأَ<tajweed class=qalaqah>بْ</tajweed>صَ<tajweed class=madda_normal>ـٰ</tajweed>رُ وَهُوَ يُ<tajweed class=qalaqah>دْ</tajweed>رِكُ <tajweed class=ham_wasl>ٱ</tajweed>لْأَ<tajweed class=qalaqah>بْ</tajweed>صَ<tajweed class=madda_normal>ـٰ</tajweed>رَ‌ۖ وَهُوَ <tajweed class=ham_wasl>ٱ</tajweed><tajweed class=laam_shamsiyah>ل</tajweed>لَّطِيفُ <tajweed class=ham_wasl>ٱ</tajweed>لْخَب<tajweed class=madda_permissible>ِي</tajweed>رُ <span class=end>١٠٣</span>","words":[{"id":72166,"verseKey":"6:103","pageNumber":141,"lineNumber":2,"position":1,"charType":"word","location":"6:103:1","textUthmani":"لَّا","textQpcHafs":"لَّا","textIndopak":"لَا","codeV1":"ﭥ","codeV2":"ﱕ"},{"id":72167,"verseKey":"6:103","pageNumber":141,"lineNumber":2,"position":2,"charType":"word","location":"6:103:2","textUthmani":"تُدْرِكُهُ","textQpcHafs":"تُدۡرِكُهُ","textIndopak":"تُدۡرِكُهُ","codeV1":"ﭦ","codeV2":"ﱖ"},{"id":72168,"verseKey":"6:103","pageNumber":141,"lineNumber":2,"position":3,"charType":"word","location":"6:103:3","textUthmani":"ٱلْأَبْصَـٰرُ","textQpcHafs":"ٱلۡأَبۡصَٰرُ","textIndopak":"الۡاَبۡصَارُ","codeV1":"ﭧ","codeV2":"ﱗ"},{"id":72169,"verseKey":"6:103","pageNumber":141,"lineNumber":2,"position":4,"charType":"word","location":"6:103:4","textUthmani":"وَهُوَ","textQpcHafs":"وَهُوَ","textIndopak":"وَهُوَ","codeV1":"ﭨ","codeV2":"ﱘ"},{"id":72170,"verseKey":"6:103","pageNumber":141,"lineNumber":3,"position":5,"charType":"word","location":"6:103:5","textUthmani":"يُدْرِكُ","textQpcHafs":"يُدۡرِكُ","textIndopak":"يُدۡرِكُ","codeV1":"ﭩ","codeV2":"ﱙ"},{"id":72171,"verseKey":"6:103","pageNumber":141,"lineNumber":3,"position":6,"charType":"word","location":"6:103:6","textUthmani":"ٱلْأَبْصَـٰرَ ۖ","textQpcHafs":"ٱلۡأَبۡصَٰرَۖ","textIndopak":"الۡاَبۡصَارَ​ۚ","codeV1":"ﭪﭫ","codeV2":"ﱚﱛ"},{"id":72173,"verseKey":"6:103","pageNumber":141,"lineNumber":3,"position":7,"charType":"word","location":"6:103:7","textUthmani":"وَهُوَ","textQpcHafs":"وَهُوَ","textIndopak":"وَهُوَ","codeV1":"ﭬ","codeV2":"ﱜ"},{"id":72174,"verseKey":"6:103","pageNumber":141,"lineNumber":3,"position":8,"charType":"word","location":"6:103:8","textUthmani":"ٱللَّطِيفُ","textQpcHafs":"ٱللَّطِيفُ","textIndopak":"اللَّطِيۡفُ","codeV1":"ﭭ","codeV2":"ﱝ"},{"id":72175,"verseKey":"6:103","pageNumber":141,"lineNumber":3,"position":9,"charType":"word","location":"6:103:9","textUthmani":"ٱلْخَبِيرُ","textQpcHafs":"ٱلۡخَبِيرُ","textIndopak":"الۡخَبِيۡرُ‏","codeV1":"ﭮ","codeV2":"ﱞ"},{"id":72176,"verseKey":"6:103","pageNumber":141,"lineNumber":3,"position":10,"charType":"end","location":"6:103:10","textUthmani":"١٠٣","textQpcHafs":"١٠٣","textIndopak":"١٠٣","codeV1":"ﭯ","codeV2":"ﱟ"}]},{"id":893,"verseKey":"6:104","chapterId":6,"pageNumber":141,"juzNumber":7,"hizbNumber":14,"rubElHizbNumber":56,"textUthmani":"قَدْ جَآءَكُم بَصَآئِرُ مِن رَّبِّكُمْ ۖ فَمَنْ أَبْصَرَ فَلِنَفْسِهِۦ ۖ وَمَنْ عَمِىَ فَعَلَيْهَا ۚ وَمَآ أَنَا۠ عَلَيْكُم بِحَفِيظٍ","textIndopak":"قَدۡ جَآءَكُمۡ بَصَآٮِٕرُ مِنۡ رَّبِّكُمۡ​ۚ فَمَنۡ اَبۡصَرَ فَلِنَفۡسِهٖ​ ۚ وَمَنۡ عَمِىَ فَعَلَيۡهَا​ ؕ وَمَاۤ اَنَا عَلَيۡكُمۡ بِحَفِيۡظٍ‏","textUthmaniTajweed":"قَ<tajweed class=qalaqah>دْ</tajweed> ج<tajweed class=madda_obligatory>َا</tajweed>ٓءَك<tajweed class=ikhafa_shafawi>ُم ب</tajweed>َص<tajweed class=madda_obligatory>َا</tajweed>ٓئِرُ م<tajweed class=idgham_wo_ghunnah>ِن ر</tajweed>َّبِّكُمْ‌ۖ فَمَنْ أَ<tajweed class=qalaqah>بْ</tajweed>صَرَ فَلِنَفْسِه<tajweed class=madda_normal>ِۦ</tajweed>‌ۖ وَمَنْ عَمِىَ فَعَلَيْهَا‌ۚ وَم<tajweed class=madda_obligatory>َآ</tajweed> أَنَا۟ عَلَيْك<tajweed class=ikhafa_shafawi>ُم ب</tajweed>ِحَف<tajweed class=madda_permissible>ِي</tajweed>ظٍ <span class=end>١٠٤</span>","words":[{"id":72517,"verseKey":"6:104","pageNumber":141,"lineNumber":3,"position":1,"charType":"word","location":"6:104:1","textUthmani":"قَدْ","textQpcHafs":"قَدۡ","textIndopak":"قَدۡ","codeV1":"ﭰ","codeV2":"ﱠ"},{"id":72518,"verseKey":"6:104","pageNumber":141,"lineNumber":3,"position":2,"charType":"word","location":"6:104:2","textUthmani":"جَآءَكُم","textQpcHafs":"جَآءَكُم","textIndopak":"جَآءَكُمۡ","codeV1":"ﭱ","codeV2":"ﱡ"},{"id":72519,"verseKey":"6:104","pageNumber":141,"lineNumber":4,"position":3,"charType":"word","location":"6:104:3","textUthmani":"بَصَآئِرُ","textQpcHafs":"بَصَآئِرُ","textIndopak":"بَصَآٮِٕرُ","codeV1":"ﭲ","codeV2":"ﱢ"},{"id":72520,"verseKey":"6:104","pageNumber":141,"lineNumber":4,"position":4,"charType":"word","location":"6:104:4","textUthmani":"مِن","textQpcHafs":"مِن","textIndopak":"مِنۡ","codeV1":"ﭳ","codeV2":"ﱣ"},{"id":72521,"verseKey":"6:104","pageNumber":141,"lineNumber":4,"position":5,"charType":"word","location":"6:104:5","textUthmani":"رَّبِّكُمْ ۖ","textQpcHafs":"رَّبِّكُمۡۖ","textIndopak":"رَّبِّكُمۡ​ۚ","codeV1":"ﭴﭵ","codeV2":"ﱤﱥ"},{"id":72523,"verseKey":"6:104","pageNumber":141,"lineNumber":4,"position":6,"charType":"word","location":"6:104:6","textUthmani":"فَمَنْ","textQpcHafs":"فَمَنۡ","textIndopak":"فَمَنۡ","codeV1":"ﭶ","codeV2":"ﱦ"},{"id":72524,"verseKey":"6:104","pageNumber":141,"lineNumber":4,"position":7,"charType":"word","location":"6:104:7","textUthmani":"أَبْصَرَ","textQpcHafs":"أَبۡصَرَ","textIndopak":"اَبۡصَرَ","codeV1":"ﭷ","codeV2":"ﱧ"},{"id":72525,"verseKey":"6:104","pageNumber":141,"lineNumber":4,"position":8,"charType":"word","location":"6:104:8","textUthmani":"فَلِنَفْسِهِۦ ۖ","textQpcHafs":"فَلِنَفۡسِهِۦۖ","textIndopak":"فَلِنَفۡسِهٖ​ ۚ","codeV1":"ﭸﭹ","codeV2":"ﱨﱩ"},{"id":72527,"verseKey":"6:104","pageNumber":141,"lineNumber":4,"position":9,"charType":"word","location":"6:104:9","textUthmani":"وَمَنْ","textQpcHafs":"وَمَنۡ","textIndopak":"وَمَنۡ","codeV1":"ﭺ","codeV2":"ﱪ"},{"id":72528,"verseKey":"6:104","pageNumber":141,"lineNumber":4,"position":10,"charType":"word","location":"6:104:10","textUthmani":"عَمِىَ","textQpcHafs":"عَمِيَ","textIndopak":"عَمِىَ","codeV1":"ﭻ","codeV2":"ﱫ"},{"id":72529,"verseKey":"6:104","pageNumber":141,"lineNumber":4,"position":11,"charType":"word","location":"6:104:11","textUthmani":"فَعَلَيْهَا ۚ","textQpcHafs":"فَعَلَيۡهَاۚ","textIndopak":"فَعَلَيۡهَا​ ؕ","codeV1":"ﭼﭽ","codeV2":"ﱬﱭ"},{"id":72531,"verseKey":"6:104","pageNumber":141,"lineNumber":5,"position":12,"charType":"word","location":"6:104:12","textUthmani":"وَمَآ","textQpcHafs":"وَمَآ","textIndopak":"وَمَاۤ","codeV1":"ﭾ","codeV2":"ﱮ"},{"id":72532,"verseKey":"6:104","pageNumber":141,"lineNumber":5,"position":13,"charType":"word","location":"6:104:13","textUthmani":"أَنَا۠","textQpcHafs":"أَنَا۠","textIndopak":"اَنَا","codeV1":"ﭿ","codeV2":"ﱯ"},{"id":72533,"verseKey":"6:104","pageNumber":141,"lineNumber":5,"position":14,"charType":"word","location":"6:104:14","textUthmani":"عَلَيْكُم","textQpcHafs":"عَلَيۡكُم","textIndopak":"عَلَيۡكُمۡ","codeV1":"ﮀ","codeV2":"ﱰ"},{"id":72534,"verseKey":"6:104","pageNumber":141,"lineNumber":5,"position":15,"charType":"word","location":"6:104:15","textUthmani":"بِحَفِيظٍۢ","textQpcHafs":"بِحَفِيظٖ","textIndopak":"بِحَفِيۡظٍ‏","codeV1":"ﮁ","codeV2":"ﱱ"},{"id":72535,"verseKey":"6:104","pageNumber":141,"lineNumber":5,"position":16,"charType":"end","location":"6:104:16","textUthmani":"١٠٤","textQpcHafs":"١٠٤","textIndopak":"١٠٤","codeV1":"ﮂ","codeV2":"ﱲ"}]},{"id":894,"verseKey":"6:105","chapterId":6,"pageNumber":141,"juzNumber":7,"hizbNumber":14,"rubElHizbNumber":56,"textUthmani":"وَكَذَٰلِكَ نُصَرِّفُ ٱلْـَٔايَـٰتِ وَلِيَقُولُوا۟ دَرَسْتَ وَلِنُبَيِّنَهُۥ لِقَوْمٍ يَعْلَمُونَ","textIndopak":"وَكَذٰلِكَ نُصَرِّفُ الۡاٰيٰتِ وَلِيَقُوۡلُوۡا دَرَسۡتَ وَلِنُبَيِّنَهٗ لِقَوۡمٍ يَّعۡلَمُوۡنَ‏","textUthmaniTajweed":"وَكَذ<tajweed class=madda_normal>َٲ</tajweed>لِكَ نُصَرِّفُ <tajweed class=ham_wasl>ٱ</tajweed>لْأَيَ<tajweed class=madda_normal>ـٰ</tajweed>تِ وَلِيَقُولُو<tajweed class=slnt>اْ</tajweed> دَرَسْتَ وَلِنُبَيِّنَهُ<tajweed class=madda_normal>ۥ</tajweed> لِقَوْ<tajweed class=idgham_ghunnah>مٍ ي</tajweed>َعْلَم<tajweed class=madda_permissible>ُو</tajweed>نَ <span class=end>١٠٥</span>","words":[{"id":72791,"verseKey":"6:105","pageNumber":141,"lineNumber":5,"position":1,"charType":"word","location":"6:105:1","textUthmani":"وَكَذَٰلِكَ","textQpcHafs":"وَكَذَٰلِكَ","textIndopak":"وَكَذٰلِكَ","codeV1":"ﮃ","codeV2":"ﱳ"},{"id":72792,"verseKey":"6:105","pageNumber":141,"lineNumber":5,"position":2,"charType":"word","location":"6:105:2","textUthmani":"نُصَرِّفُ","textQpcHafs":"نُصَرِّفُ","textIndopak":"نُصَرِّفُ","codeV1":"ﮄ","codeV2":"ﱴ"},{"id":72793,"verseKey":"6:105","pageNumber":141,"lineNumber":5,"position":3,"charType":"word","location":"6:105:3","textUthmani":"ٱلْـَٔايَـٰتِ","textQpcHafs":"ٱلۡأٓيَٰتِ","textIndopak":"الۡاٰيٰتِ","codeV1":"ﮅ","codeV2":"ﱵ"},{"id":72794,"verseKey":"6:105","pageNumber":141,"lineNumber":6,"position":4,"charType":"word","location":"6:105:4","textUthmani":"وَلِيَقُولُوا۟","textQpcHafs":"وَلِيَقُولُواْ","textIndopak":"وَلِيَقُوۡلُوۡا","codeV1":"ﮆ","codeV2":"ﱶ"},{"id":72795,"verseKey":"6:105","pageNumber":141,"lineNumber":6,"position":5,"charType":"word","location":"6:105:5","textUthmani":"دَرَسْتَ","textQpcHafs":"دَرَسۡتَ","textIndopak":"دَرَسۡتَ","codeV1":"ﮇ","codeV2":"ﱷ"},{"id":72796,"verseKey":"6:105","pageNumber":141,"lineNumber":6,"position":6,"charType":"word","location":"6:105:6","textUthmani":"وَلِنُبَيِّنَهُۥ","textQpcHafs":"وَلِنُبَيِّنَهُۥ","textIndopak":"وَلِنُبَيِّنَهٗ","codeV1":"ﮈ","codeV2":"ﱸ"},{"id":72797,"verseKey":"6:105","pageNumber":141,"lineNumber":6,"position":7,"charType":"word","location":"6:105:7","textUthmani":"لِقَوْمٍۢ","textQpcHafs":"لِقَوۡمٖ","textIndopak":"لِقَوۡمٍ","codeV1":"ﮉ","codeV2":"ﱹ"},{"id":72798,"verseKey":"6:105","pageNumber":141,"lineNumber":6,"position":8,"charType":"word","location":"6:105:8","textUthmani":"يَعْلَمُونَ","textQpcHafs":"يَعۡلَمُونَ","textIndopak":"يَّعۡلَمُوۡنَ‏","codeV1":"ﮊ","codeV2":"ﱺ"},{"id":72799,"verseKey":"6:105","pageNumber":141,"lineNumber":6,"position":9,"charType":"end","location":"6:105:9","textUthmani":"١٠٥","textQpcHafs":"١٠٥","textIndopak":"١٠٥","codeV1":"ﮋ","codeV2":"ﱻ"}]},{"id":895,"verseKey":"6:106","chapterId":6,"pageNumber":141,"juzNumber":7,"hizbNumber":14,"rubElHizbNumber":56,"textUthmani":"ٱتَّبِعْ مَآ أُوحِىَ إِلَيْكَ مِن رَّبِّكَ ۖ لَآ إِلَـٰهَ إِلَّا هُوَ ۖ وَأَعْرِضْ عَنِ ٱلْمُشْرِكِينَ","textIndopak":"اِتَّبِعۡ مَاۤ اُوۡحِىَ اِلَيۡكَ مِنۡ رَّبِّكَ​​ۚ لَاۤ اِلٰهَ اِلَّا هُوَ​ۚ وَاَعۡرِضۡ عَنِ الۡمُشۡرِكِيۡنَ‏","textUthmaniTajweed":"ٱتَّبِعْ م<tajweed class=madda_obligatory>َآ</tajweed> أُوحِىَ إِلَيْكَ م<tajweed class=idgham_wo_ghunnah>ِن ر</tajweed>َّبِّكَ‌ۖ ل<tajweed class=madda_obligatory>َآ</tajweed> إِلَ<tajweed class=madda_normal>ـٰ</tajweed>هَ إِلَّا هُوَ‌ۖ وَأَعْرِضْ عَنِ <tajweed class=ham_wasl>ٱ</tajweed>لْمُشْرِك<tajweed class=madda_permissible>ِي</tajweed>نَ <span class=end>١٠٦</span>","words":[{"id":72988,"verseKey":"6:106","pageNumber":141,"lineNumber":6,"position":1,"charType":"word","location":"6:106:1","textUthmani":"ٱتَّبِعْ","textQpcHafs":"ٱتَّبِعۡ","textIndopak":"اِتَّبِعۡ","codeV1":"ﮌ","codeV2":"ﱼ"},{"id":72989,"verseKey":"6:106","pageNumber":141,"lineNumber":7,"position":2,"charType":"word","location":"6:106:2","textUthmani":"مَآ","textQpcHafs":"مَآ","textIndopak":"مَاۤ","codeV1":"ﮍ","codeV2":"ﱽ"},{"id":72990,"verseKey":"6:106","pageNumber":141,"lineNumber":7,"position":3,"charType":"word","location":"6:106:3","textUthmani":"أُوحِىَ","textQpcHafs":"أُوحِيَ","textIndopak":"اُوۡحِىَ","codeV1":"ﮎ","codeV2":"ﱾ"},{"id":72991,"verseKey":"6:106","pageNumber":141,"lineNumber":7,"position":4,"charType":"word","location":"6:106:4","textUthmani":"إِلَيْكَ","textQpcHafs":"إِلَيۡكَ","textIndopak":"اِلَيۡكَ","codeV1":"ﮏ","codeV2":"ﱿ"},{"id":72992,"verseKey":"6:106","pageNumber":141,"lineNumber":7,"position":5,"charType":"word","location":"6:106:5","textUthmani":"مِن","textQpcHafs":"مِن","textIndopak":"مِنۡ","codeV1":"ﮐ","codeV2":"ﲀ"},{"id":72993,"verseKey":"6:106","pageNumber":141,"lineNumber":7,"position":6,"charType":"word","location":"6:106:6","textUthmani":"رَّبِّكَ ۖ","textQpcHafs":"رَّبِّكَۖ","textIndopak":"رَّبِّكَ​​ۚ","codeV1":"ﮑﮒ","codeV2":"ﲁﲂ"},{"id":72995,"verseKey":"6:106","pageNumber":141,"lineNumber":7,"position":7,"charType":"word","location":"6:106:7","textUthmani":"لَآ","textQpcHafs":"لَآ","textIndopak":"لَاۤ","codeV1":"ﮓ","codeV2":"ﲃ"},{"id":72996,"verseKey":"6:106","pageNumber":141,"lineNumber":7,"position":8,"charType":"word","location":"6:106:8","textUthmani":"إِلَـٰهَ","textQpcHafs":"إِلَٰهَ","textIndopak":"اِلٰهَ","codeV1":"ﮔ","codeV2":"ﲄ"},{"id":72997,"verseKey":"6:106","pageNumber":141,"lineNumber":7,"position":9,"charType":"word","location":"6:106:9","textUthmani":"إِلَّا","textQpcHafs":"إِلَّا","textIndopak":"اِلَّا","codeV1":"ﮕ","codeV2":"ﲅ"},{"id":72998,"verseKey":"6:106","pageNumber":141,"lineNumber":7,"position":10,"charType":"word","location":"6:106:10","textUthmani":"هُوَ ۖ","textQpcHafs":"هُوَۖ","textIndopak":"هُوَ​ۚ","codeV1":"ﮖﮗ","codeV2":"ﲆﲇ"},{"id":73000,"verseKey":"6:106","pageNumber":141,"lineNumber":7,"position":11,"charType":"word","location":"6:106:11","textUthmani":"وَأَعْرِضْ","textQpcHafs":"وَأَعۡرِضۡ","textIndopak":"وَاَعۡرِضۡ","codeV1":"ﮘ","codeV2":"ﲈ"},{"id":73001,"verseKey":"6:106","pageNumber":141,"lineNumber":7,"position":12,"charType":"word","location":"6:106:12","textUthmani":"عَنِ","textQpcHafs":"عَنِ","textIndopak":"عَنِ","codeV1":"ﮙ","codeV2":"ﲉ"},{"id":73002,"verseKey":"6:106","pageNumber":141,"lineNumber":7,"position":13,"charType":"word","location":"6:106:13","textUthmani":"ٱلْمُشْرِكِينَ","textQpcHafs":"ٱلۡمُشۡرِكِينَ","textIndopak":"الۡمُشۡرِكِيۡنَ‏","codeV1":"ﮚ","codeV2":"ﲊ"},{"id":73003,"verseKey":"6:106","pageNumber":141,"lineNumber":8,"position":14,"charType":"end","location":"6:106:14","textUthmani":"١٠٦","textQpcHafs":"١٠٦","textIndopak":"١٠٦","codeV1":"ﮛ","codeV2":"ﲋ"}]},{"id":896,"verseKey":"6:107","chapterId":6,"pageNumber":141,"juzNumber":7,"hizbNumber":14,"rubElHizbNumber":56,"textUthmani":"وَلَوْ شَآءَ ٱللَّهُ مَآ أَشْرَكُوا۟ ۗ وَمَا جَعَلْنَـٰكَ عَلَيْهِمْ حَفِيظًا ۖ وَمَآ أَنتَ عَلَيْهِم بِوَكِيلٍ","textIndopak":"وَلَوۡ شَآءَ اللّٰهُ مَاۤ اَشۡرَكُوۡا ​ؕ وَمَا جَعَلۡنٰكَ عَلَيۡهِمۡ حَفِيۡظًا​ ۚ وَمَاۤ اَنۡتَ عَلَيۡهِمۡ بِوَكِيۡلٍ‏","textUthmaniTajweed":"وَلَوْ ش<tajweed class=madda_obligatory>َا</tajweed>ٓءَ <tajweed class=ham_wasl>ٱ</tajweed>للَّهُ م<tajweed class=madda_obligatory>َآ</tajweed> أَشْرَكُو<tajweed class=slnt>اْ‌ۗ</tajweed> وَمَا جَعَلْنَ<tajweed class=madda_normal>ـٰ</tajweed>كَ عَلَيْهِمْ حَفِي<tajweed class=idgham_ghunnah>ظًا‌ۖ و</tajweed>َم<tajweed class=madda_obligatory>َآ</tajweed> أَ<tajweed class=ikhafa>نت</tajweed>َ عَلَيْه<tajweed class=ikhafa_shafawi>ِم ب</tajweed>ِوَك<tajweed class=madda_permissible>ِي</tajweed>لٍ <span class=end>١٠٧</span>","words":[{"id":73261,"verseKey":"6:107","pageNumber":141,"lineNumber":8,"position":1,"charType":"word","location":"6:107:1","textUthmani":"وَلَوْ","textQpcHafs":"وَلَوۡ","textIndopak":"وَلَوۡ","codeV1":"ﮜ","codeV2":"ﲌ"},{"id":73262,"verseKey":"6:107","pageNumber":141,"lineNumber":8,"position":2,"charType":"word","location":"6:107:2","textUthmani":"شَآءَ","textQpcHafs":"شَآءَ","textIndopak":"شَآءَ","codeV1":"ﮝ","codeV2":"ﲍ"},{"id":73263,"verseKey":"6:107","pageNumber":141,"lineNumber":8,"position":3,"charType":"word","location":"6:107:3","textUthmani":"ٱللَّهُ","textQpcHafs":"ٱللَّهُ","textIndopak":"اللّٰهُ","codeV1":"ﮞ","codeV2":"ﲎ"},{"id":73264,"verseKey":"6:107","pageNumber":141,"lineNumber":8,"position":4,"charType":"word","location":"6:107:4","textUthmani":"مَآ","textQpcHafs":"مَآ","textIndopak":"مَاۤ","codeV1":"ﮟ","codeV2":"ﲏ"},{"id":73265,"verseKey":"6:107","pageNumber":141,"lineNumber":8,"position":5,"charType":"word","location":"6:107:5","textUthmani":"أَشْرَكُوا۟ ۗ","textQpcHafs":"أَشۡرَكُواْۗ","textIndopak":"اَشۡرَكُوۡا ​ؕ","codeV1":"ﮠﮡ","codeV2":"ﲐﲑ"},{"id":73267,"verseKey":"6:107","pageNumber":141,"lineNumber":8,"position":6,"charType":"word","location":"6:107:6","textUthmani":"وَمَا","textQpcHafs":"وَمَا","textIndopak":"وَمَا","codeV1":"ﮢ","codeV2":"ﲒ"},{"id":73268,"verseKey":"6:107","pageNumber":141,"lineNumber":8,"position":7,"charType":"word","location":"6:107:7","textUthmani":"جَعَلْنَـٰكَ","textQpcHafs":"جَعَلۡنَٰكَ","textIndopak":"جَعَلۡنٰكَ","codeV1":"ﮣ","codeV2":"ﲓ"},{"id":73269,"verseKey":"6:107","pageNumber":141,"lineNumber":8,"position":8,"charType":"word","location":"6:107:8","textUthmani":"عَلَيْهِمْ","textQpcHafs":"عَلَيۡهِمۡ","textIndopak":"عَلَيۡهِمۡ","codeV1":"ﮤ","codeV2":"ﲔ"},{"id":73270,"verseKey":"6:107","pageNumber":141,"lineNumber":8,"position":9,"charType":"word","location":"6:107:9","textUthmani":"حَفِيظًۭا ۖ","textQpcHafs":"حَفِيظٗاۖ","textIndopak":"حَفِيۡظًا​ ۚ","codeV1":"ﮥﮦ","codeV2":"ﲕﲖ"},{"id":73272,"verseKey":"6:107","pageNumber":141,"lineNumber":9,"position":10,"charType":"word","location":"6:107:10","textUthmani":"وَمَآ","textQpcHafs":"وَمَآ","textIndopak":"وَمَاۤ","codeV1":"ﮧ","codeV2":"ﲗ"},{"id":73273,"verseKey":"6:107","pageNumber":141,"lineNumber":9,"position":11,"charType":"word","location":"6:107:11","textUthmani":"أَنتَ","textQpcHafs":"أَنتَ","textIndopak":"اَنۡتَ","codeV1":"ﮨ","codeV2":"ﲘ"},{"id":73274,"verseKey":"6:107","pageNumber":141,"lineNumber":9,"position":12,"charType":"word","location":"6:107:12","textUthmani":"عَلَيْهِم","textQpcHafs":"عَلَيۡهِم","textIndopak":"عَلَيۡهِمۡ","codeV1":"ﮩ","codeV2":"ﲙ"},{"id":73275,"verseKey":"6:107","pageNumber":141,"lineNumber":9,"position":13,"charType":"word","location":"6:107:13","textUthmani":"بِوَكِيلٍۢ","textQpcHafs":"بِوَكِيلٖ","textIndopak":"بِوَكِيۡلٍ‏","codeV1":"ﮪ","codeV2":"ﲚ"},{"id":73276,"verseKey":"6:107","pageNumber":141,"lineNumber":9,"position":14,"charType":"end","location":"6:107:14","textUthmani":"١٠٧","textQpcHafs":"١٠٧","textIndopak":"١٠٧","codeV1":"ﮫ","codeV2":"ﲛ"}]},{"id":897,"verseKey":"6:108","chapterId":6,"pageNumber":141,"juzNumber":7,"hizbNumber":14,"rubElHizbNumber":56,"textUthmani":"وَلَا تَسُبُّوا۟ ٱلَّذِينَ يَدْعُونَ مِن دُونِ ٱللَّهِ فَيَسُبُّوا۟ ٱللَّهَ عَدْوًۢا بِغَيْرِ عِلْمٍ ۗ كَذَٰلِكَ زَيَّنَّا لِكُلِّ أُمَّةٍ عَمَلَهُمْ ثُمَّ إِلَىٰ رَبِّهِم مَّرْجِعُهُمْ فَيُنَبِّئُهُم بِمَا كَانُوا۟ يَعْمَلُونَ","textIndopak":"وَلَا تَسُبُّوا الَّذِيۡنَ يَدۡعُوۡنَ مِنۡ دُوۡنِ اللّٰهِ فَيَسُبُّوا اللّٰهَ عَدۡوًاۢ بِغَيۡرِ عِلۡمٍ ​ؕ كَذٰلِكَ زَيَّنَّا لِكُلِّ اُمَّةٍ عَمَلَهُمۡ ثُمَّ اِلٰى رَبِّهِمۡ مَّرۡجِعُهُمۡ فَيُنَبِّئُهُمۡ بِمَا كَانُوۡا يَعۡمَلُوۡنَ‏","textUthmaniTajweed":"وَلَا تَسُبُّو<tajweed class=slnt>اْ</tajweed> <tajweed class=ham_wasl>ٱ</tajweed>لَّذِينَ يَ<tajweed class=qalaqah>دْ</tajweed>عُونَ مِ<tajweed class=ikhafa>ن د</tajweed>ُونِ <tajweed class=ham_wasl>ٱ</tajweed>للَّهِ فَيَسُبُّو<tajweed class=slnt>اْ</tajweed> <tajweed class=ham_wasl>ٱ</tajweed>للَّهَ عَ<tajweed class=qalaqah>دْ</tajweed>و<tajweed class=iqlab>َۢا ب</tajweed>ِغَيْرِ عِلْ<tajweed class=ikhafa>مٍ‌ۗ ك</tajweed>َذ<tajweed class=madda_normal>َٲ</tajweed>لِكَ زَيَّ<tajweed class=ghunnah>نّ</tajweed>َا لِكُلِّ أُ<tajweed class=ghunnah>مّ</tajweed>َةٍ عَمَلَهُمْ ثُ<tajweed class=ghunnah>مّ</tajweed>َ إِلَىٰ رَبِّه<tajweed class=idgham_shafawi>ِم م</tajweed>َّرْجِعُهُمْ فَيُنَبِّئُه<tajweed class=ikhafa_shafawi>ُم ب</tajweed>ِمَا كَانُو<tajweed class=slnt>اْ</tajweed> يَعْمَل<tajweed class=madda_permissible>ُو</tajweed>نَ <span class=end>١٠٨</span>","words":[{"id":73499,"verseKey":"6:108","pageNumber":141,"lineNumber":9,"position":1,"charType":"word","location":"6:108:1","textUthmani":"وَلَا","textQpcHafs":"وَلَا","textIndopak":"وَلَا","codeV1":"ﮬ","codeV2":"ﲜ"},{"id":73500,"verseKey":"6:108","pageNumber":141,"lineNumber":9,"position":2,"charType":"word","location":"6:108:2","textUthmani":"تَسُبُّوا۟","textQpcHafs":"تَسُبُّواْ","textIndopak":"تَسُبُّوا","codeV1":"ﮭ","codeV2":"ﲝ"},{"id":73501,"verseKey":"6:108","pageNumber":141,"lineNumber":9,"position":3,"charType":"word","location":"6:108:3","textUthmani":"ٱلَّذِينَ","textQpcHafs":"ٱلَّذِينَ","textIndopak":"الَّذِيۡنَ","codeV1":"ﮮ","codeV2":"ﲞ"},{"id":73502,"verseKey":"6:108","pageNumber":141,"lineNumber":9,"position":4,"charType":"word","location":"6:108:4","textUthmani":"يَدْعُونَ","textQpcHafs":"يَدۡعُونَ","textIndopak":"يَدۡعُوۡنَ","codeV1":"ﮯ","codeV2":"ﲟ"},{"id":73503,"verseKey":"6:108","pageNumber":141,"lineNumber":10,"position":5,"charType":"word","location":"6:108:5","textUthmani":"مِن","textQpcHafs":"مِن","textIndopak":"مِنۡ","codeV1":"ﮰ","codeV2":"ﲠ"},{"id":73504,"verseKey":"6:108","pageNumber":141,"lineNumber":10,"position":6,"charType":"word","location":"6:108:6","textUthmani":"دُونِ","textQpcHafs":"دُونِ","textIndopak":"دُوۡنِ","codeV1":"ﮱ","codeV2":"ﲡ"},{"id":73505,"verseKey":"6:108","pageNumber":141,"lineNumber":10,"position":7,"charType":"word","location":"6:108:7","textUthmani":"ٱللَّهِ","textQpcHafs":"ٱللَّهِ","textIndopak":"اللّٰهِ","codeV1":"ﯓ","codeV2":"ﲢ"},{"id":73506,"verseKey":"6:108","pageNumber":141,"lineNumber":10,"position":8,"charType":"word","location":"6:108:8","textUthmani":"فَيَسُبُّوا۟","textQpcHafs":"فَيَسُبُّواْ","textIndopak":"فَيَسُبُّوا","codeV1":"ﯔ","codeV2":"ﲣ"},{"id":73507,"verseKey":"6:108","pageNumber":141,"lineNumber":10,"position":9,"charType":"word","location":"6:108:9","textUthmani":"ٱللَّهَ","textQpcHafs":"ٱللَّهَ","textIndopak":"اللّٰهَ","codeV1":"ﯕ","codeV2":"ﲤ"},{"id":73508,"verseKey":"6:108","pageNumber":141,"lineNumber":10,"position":10,"charType":"word","location":"6:108:10","textUthmani":"عَدْوًۢا","textQpcHafs":"عَدۡوَۢا","textIndopak":"عَدۡوًاۢ","codeV1":"ﯖ","codeV2":"ﲥ"},{"id":73509,"verseKey":"6:108","pageNumber":141,"lineNumber":10,"position":11,"charType":"word","location":"6:108:11","textUthmani":"بِغَيْرِ","textQpcHafs":"بِغَيۡرِ","textIndopak":"بِغَيۡرِ","codeV1":"ﯗ","codeV2":"ﲦ"},{"id":73510,"verseKey":"6:108","pageNumber":141,"lineNumber":10,"position":12,"charType":"word","location":"6:108:12","textUthmani":"عِلْمٍۢ ۗ","textQpcHafs":"عِلۡمٖۗ","textIndopak":"عِلۡمٍ ​ؕ","codeV1":"ﯘﯙ","codeV2":"ﲧﲨ"},{"id":73512,"verseKey":"6:108","pageNumber":141,"lineNumber":10,"position":13,"charType":"word","location":"6:108:13","textUthmani":"كَذَٰلِكَ","textQpcHafs":"كَذَٰلِكَ","textIndopak":"كَذٰلِكَ","codeV1":"ﯚ","codeV2":"ﲩ"},{"id":73513,"verseKey":"6:108","pageNumber":141,"lineNumber":10,"position":14,"charType":"word","location":"6:108:14","textUthmani":"زَيَّنَّا","textQpcHafs":"زَيَّنَّا","textIndopak":"زَيَّنَّا","codeV1":"ﯛ","codeV2":"ﲪ"},{"id":73514,"verseKey":"6:108","pageNumber":141,"lineNumber":10,"position":15,"charType":"word","location":"6:108:15","textUthmani":"لِكُلِّ","textQpcHafs":"لِكُلِّ","textIndopak":"لِكُلِّ","codeV1":"ﯜ","codeV2":"ﲫ"},{"id":73515,"verseKey":"6:108","pageNumber":141,"lineNumber":10,"position":16,"charType":"word","location":"6:108:16","textUthmani":"أُمَّةٍ","textQpcHafs":"أُمَّةٍ","textIndopak":"اُمَّةٍ","codeV1":"ﯝ","codeV2":"ﲬ"},{"id":73516,"verseKey":"6:108","pageNumber":141,"lineNumber":11,"position":17,"charType":"word","location":"6:108:17","textUthmani":"عَمَلَهُمْ","textQpcHafs":"عَمَلَهُمۡ","textIndopak":"عَمَلَهُمۡ","codeV1":"ﯞ","codeV2":"ﲭ"},{"id":73517,"verseKey":"6:108","pageNumber":141,"lineNumber":11,"position":18,"charType":"word","location":"6:108:18","textUthmani":"ثُمَّ","textQpcHafs":"ثُمَّ","textIndopak":"ثُمَّ","codeV1":"ﯟ","codeV2":"ﲮ"},{"id":73518,"verseKey":"6:108","pageNumber":141,"lineNumber":11,"position":19,"charType":"word","location":"6:108:19","textUthmani":"إِلَىٰ","textQpcHafs":"إِلَىٰ","textIndopak":"اِلٰى","codeV1":"ﯠ","codeV2":"ﲯ"},{"id":73519,"verseKey":"6:108","pageNumber":141,"lineNumber":11,"position":20,"charType":"word","location":"6:108:20","textUthmani":"رَبِّهِم","textQpcHafs":"رَبِّهِم","textIndopak":"رَبِّهِمۡ","codeV1":"ﯡ","codeV2":"ﲰ"},{"id":73520,"verseKey":"6:108","pageNumber":141,"lineNumber":11,"position":21,"charType":"word","location":"6:108:21","textUthmani":"مَّرْجِعُهُمْ","textQpcHafs":"مَّرۡجِعُهُمۡ","textIndopak":"مَّرۡجِعُهُمۡ","codeV1":"ﯢ","codeV2":"ﲱ"},{"id":73521,"verseKey":"6:108","pageNumber":141,"lineNumber":11,"position":22,"charType":"word","location":"6:108:22","textUthmani":"فَيُنَبِّئُهُم","textQpcHafs":"فَيُنَبِّئُهُم","textIndopak":"فَيُنَبِّئُهُمۡ","codeV1":"ﯣ","codeV2":"ﲲ"},{"id":73522,"verseKey":"6:108","pageNumber":141,"lineNumber":11,"position":23,"charType":"word","location":"6:108:23","textUthmani":"بِمَا","textQpcHafs":"بِمَا","textIndopak":"بِمَا","codeV1":"ﯤ","codeV2":"ﲳ"},{"id":73523,"verseKey":"6:108","pageNumber":141,"lineNumber":11,"position":24,"charType":"word","location":"6:108:24","textUthmani":"كَانُوا۟","textQpcHafs":"كَانُواْ","textIndopak":"كَانُوۡا","codeV1":"ﯥ","codeV2":"ﲴ"},{"id":73524,"verseKey":"6:108","pageNumber":141,"lineNumber":11,"position":25,"charType":"word","location":"6:108:25","textUthmani":"يَعْمَلُونَ","textQpcHafs":"يَعۡمَلُونَ","textIndopak":"يَعۡمَلُوۡنَ‏","codeV1":"ﯦ","codeV2":"ﲵ"},{"id":73525,"verseKey":"6:108","pageNumber":141,"lineNumber":12,"position":26,"charType":"end","location":"6:108:26","textUthmani":"١٠٨","textQpcHafs":"١٠٨","textIndopak":"١٠٨","codeV1":"ﯧ","codeV2":"ﲶ"}]},{"id":898,"verseKey":"6:109","chapterId":6,"pageNumber":141,"juzNumber":7,"hizbNumber":14,"rubElHizbNumber":56,"textUthmani":"وَأَقْسَمُوا۟ بِٱللَّهِ جَهْدَ أَيْمَـٰنِهِمْ لَئِن جَآءَتْهُمْ ءَايَةٌ لَّيُؤْمِنُنَّ بِهَا ۚ قُلْ إِنَّمَا ٱلْـَٔايَـٰتُ عِندَ ٱللَّهِ ۖ وَمَا يُشْعِرُكُمْ أَنَّهَآ إِذَا جَآءَتْ لَا يُؤْمِنُونَ","textIndopak":"وَاَقۡسَمُوۡا بِاللّٰهِ جَهۡدَ اَيۡمَانِهِمۡ لَٮِٕنۡ جَآءَتۡهُمۡ اٰيَةٌ لَّيُؤۡمِنُنَّ بِهَا​ ؕ قُلۡ اِنَّمَا الۡاٰيٰتُ عِنۡدَ اللّٰهِ​ وَمَا يُشۡعِرُكُمۙۡ اَنَّهَاۤ اِذَا جَآءَتۡ لَا يُؤۡمِنُوۡنَ‏","textUthmaniTajweed":"وَأَ<tajweed class=qalaqah>قْ</tajweed>سَمُو<tajweed class=slnt>اْ</tajweed> بِ<tajweed class=ham_wasl>ٱ</tajweed>للَّهِ جَهْدَ أَيْمَ<tajweed class=madda_normal>ـٰ</tajweed>نِهِمْ لَئِ<tajweed class=ikhafa>ن ج</tajweed><tajweed class=madda_obligatory>َا</tajweed>ٓءَتْهُمْ ءَايَ<tajweed class=idgham_wo_ghunnah>ةٌ ل</tajweed>َّيُؤْمِنُ<tajweed class=ghunnah>نّ</tajweed>َ بِهَا‌ۚ قُلْ إِ<tajweed class=ghunnah>نّ</tajweed>َمَا <tajweed class=ham_wasl>ٱ</tajweed>لْأَيَ<tajweed class=madda_normal>ـٰ</tajweed>تُ عِ<tajweed class=ikhafa>ند</tajweed>َ <tajweed class=ham_wasl>ٱ</tajweed>للَّهِ‌ۖ وَمَا يُشْعِرُكُمْ أَ<tajweed class=ghunnah>نّ</tajweed>َه<tajweed class=madda_obligatory>َآ</tajweed> إِذَا ج<tajweed class=madda_obligatory>َا</tajweed>ٓءَتْ لَا يُؤْمِن<tajweed class=madda_permissible>ُو</tajweed>نَ <span class=end>١٠٩</span>","words":[{"id":73904,"verseKey":"6:109","pageNumber":141,"lineNumber":12,"position":1,"charType":"word","location":"6:109:1","textUthmani":"وَأَقْسَمُوا۟","textQpcHafs":"وَأَقۡسَمُواْ","textIndopak":"وَاَقۡسَمُوۡا","codeV1":"ﯨ","codeV2":"ﲷ"},{"id":73905,"verseKey":"6:109","pageNumber":141,"lineNumber":12,"position":2,"charType":"word","location":"6:109:2","textUthmani":"بِٱللَّهِ","textQpcHafs":"بِٱللَّهِ","textIndopak":"بِاللّٰهِ","codeV1":"ﯩ","codeV2":"ﲸ"},{"id":73906,"verseKey":"6:109","pageNumber":141,"lineNumber":12,"position":3,"charType":"word","location":"6:109:3","textUthmani":"جَهْدَ","textQpcHafs":"جَهۡدَ","textIndopak":"جَهۡدَ","codeV1":"ﯪ","codeV2":"ﲹ"},{"id":73907,"verseKey":"6:109","pageNumber":141,"lineNumber":12,"position":4,"charType":"word","location":"6:109:4","textUthmani":"أَيْمَـٰنِهِمْ","textQpcHafs":"أَيۡمَٰنِهِمۡ","textIndopak":"اَيۡمَانِهِمۡ","codeV1":"ﯫ","codeV2":"ﲺ"},{"id":73908,"verseKey":"6:109","pageNumber":141,"lineNumber":12,"position":5,"charType":"word","location":"6:109:5","textUthmani":"لَئِن","textQpcHafs":"لَئِن","textIndopak":"لَٮِٕنۡ","codeV1":"ﯬ","codeV2":"ﲻ"},{"id":73909,"verseKey":"6:109","pageNumber":141,"lineNumber":12,"position":6,"charType":"word","location":"6:109:6","textUthmani":"جَآءَتْهُمْ","textQpcHafs":"جَآءَتۡهُمۡ","textIndopak":"جَآءَتۡهُمۡ","codeV1":"ﯭ","codeV2":"ﲼ"},{"id":73910,"verseKey":"6:109","pageNumber":141,"lineNumber":12,"position":7,"charType":"word","location":"6:109:7","textUthmani":"ءَايَةٌۭ","textQpcHafs":"ءَايَةٞ","textIndopak":"اٰيَةٌ","codeV1":"ﯮ","codeV2":"ﲽ"},{"id":73911,"verseKey":"6:109","pageNumber":141,"lineNumber":12,"position":8,"charType":"word","location":"6:109:8","textUthmani":"لَّيُؤْمِنُنَّ","textQpcHafs":"لَّيُؤۡمِنُنَّ","textIndopak":"لَّيُؤۡمِنُنَّ","codeV1":"ﯯ","codeV2":"ﲾ"},{"id":73912,"verseKey":"6:109","pageNumber":141,"lineNumber":13,"position":9,"charType":"word","location":"6:109:9","textUthmani":"بِهَا ۚ","textQpcHafs":"بِهَاۚ","textIndopak":"بِهَا​ ؕ","codeV1":"ﯰﯱ","codeV2":"ﲿﳀ"},{"id":73914,"verseKey":"6:109","pageNumber":141,"lineNumber":13,"position":10,"charType":"word","location":"6:109:10","textUthmani":"قُلْ","textQpcHafs":"قُلۡ","textIndopak":"قُلۡ","codeV1":"ﯲ","codeV2":"ﳁ"},{"id":73915,"verseKey":"6:109","pageNumber":141,"lineNumber":13,"position":11,"charType":"word","location":"6:109:11","textUthmani":"إِنَّمَا","textQpcHafs":"إِنَّمَا","textIndopak":"اِنَّمَا","codeV1":"ﯳ","codeV2":"ﳂ"},{"id":73916,"verseKey":"6:109","pageNumber":141,"lineNumber":13,"position":12,"charType":"word","location":"6:109:12","textUthmani":"ٱلْـَٔايَـٰتُ","textQpcHafs":"ٱلۡأٓيَٰتُ","textIndopak":"الۡاٰيٰتُ","codeV1":"ﯴ","codeV2":"ﳃ"},{"id":73917,"verseKey":"6:109","pageNumber":141,"lineNumber":13,"position":13,"charType":"word","location":"6:109:13","textUthmani":"عِندَ","textQpcHafs":"عِندَ","textIndopak":"عِنۡدَ","codeV1":"ﯵ","codeV2":"ﳄ"},{"id":73918,"verseKey":"6:109","pageNumber":141,"lineNumber":13,"position":14,"charType":"word","location":"6:109:14","textUthmani":"ٱللَّهِ ۖ","textQpcHafs":"ٱللَّهِۖ","textIndopak":"اللّٰهِ​","codeV1":"ﯶﯷ","codeV2":"ﳅﳆ"},{"id":73920,"verseKey":"6:109","pageNumber":141,"lineNumber":13,"position":15,"charType":"word","location":"6:109:15","textUthmani":"وَمَا","textQpcHafs":"وَمَا","textIndopak":"وَمَا","codeV1":"ﯸ","codeV2":"ﳇ"},{"id":73921,"verseKey":"6:109","pageNumber":141,"lineNumber":13,"position":16,"charType":"word","location":"6:109:16","textUthmani":"يُشْعِرُكُمْ","textQpcHafs":"يُشۡعِرُكُمۡ","textIndopak":"يُشۡعِرُكُمۙۡ","codeV1":"ﯹ","codeV2":"ﳈ"},{"id":73922,"verseKey":"6:109","pageNumber":141,"lineNumber":13,"position":17,"charType":"word","location":"6:109:17","textUthmani":"أَنَّهَآ","textQpcHafs":"أَنَّهَآ","textIndopak":"اَنَّهَاۤ","codeV1":"ﯺ","codeV2":"ﳉ"},{"id":73923,"verseKey":"6:109","pageNumber":141,"lineNumber":13,"position":18,"charType":"word","location":"6:109:18","textUthmani":"إِذَا","textQpcHafs":"إِذَا","textIndopak":"اِذَا","codeV1":"ﯻ","codeV2":"ﳊ"},{"id":73924,"verseKey":"6:109","pageNumber":141,"lineNumber":13,"position":19,"charType":"word","location":"6:109:19","textUthmani":"جَآءَتْ","textQpcHafs":"جَآءَتۡ","textIndopak":"جَآءَتۡ","codeV1":"ﯼ","codeV2":"ﳋ"},{"id":73925,"verseKey":"6:109","pageNumber":141,"lineNumber":14,"position":20,"charType":"word","location":"6:109:20","textUthmani":"لَا","textQpcHafs":"لَا","textIndopak":"لَا","codeV1":"ﯽ","codeV2":"ﳌ"},{"id":73926,"verseKey":"6:109","pageNumber":141,"lineNumber":14,"position":21,"charType":"word","location":"6:109:21","textUthmani":"يُؤْمِنُونَ","textQpcHafs":"يُؤۡمِنُونَ","textIndopak":"يُؤۡمِنُوۡنَ‏","codeV1":"ﯾ","codeV2":"ﳍ"},{"id":73927,"verseKey":"6:109","pageNumber":141,"lineNumber":14,"position":22,"charType":"end","location":"6:109:22","textUthmani":"١٠٩","textQpcHafs":"١٠٩","textIndopak":"١٠٩","codeV1":"ﯿ","codeV2":"ﳎ"}]},{"id":899,"verseKey":"6:110","chapterId":6,"pageNumber":141,"juzNumber":7,"hizbNumber":14,"rubElHizbNumber":56,"textUthmani":"وَنُقَلِّبُ أَفْـِٔدَتَهُمْ وَأَبْصَـٰرَهُمْ كَمَا لَمْ يُؤْمِنُوا۟ بِهِۦٓ أَوَّلَ مَرَّةٍ وَنَذَرُهُمْ فِى طُغْيَـٰنِهِمْ يَعْمَهُونَ","textIndopak":"وَنُقَلِّبُ اَفۡـــِٕدَتَهُمۡ وَاَبۡصَارَهُمۡ كَمَا لَمۡ يُؤۡمِنُوۡا بِهٖۤ اَوَّلَ مَرَّةٍ وَّنَذَرُهُمۡ فِىۡ طُغۡيَانِهِمۡ يَعۡمَهُوۡنَ‏","textUthmaniTajweed":"وَنُقَلِّبُ أَفْــِٔدَتَهُمْ وَأَ<tajweed class=qalaqah>بْ</tajweed>صَ<tajweed class=madda_normal>ـٰ</tajweed>رَهُمْ كَمَا لَمْ يُؤْمِنُو<tajweed class=slnt>اْ</tajweed> بِه<tajweed class=madda_obligatory>ِۦٓ</tajweed> أَوَّلَ مَرَّ<tajweed class=idgham_ghunnah>ةٍ و</tajweed>َنَذَرُهُمْ فِى طُغْيَ<tajweed class=madda_normal>ـٰ</tajweed>نِهِمْ يَعْمَه<tajweed class=madda_permissible>ُو</tajweed>نَ <span class=end>١١٠</span>","words":[{"id":74095,"verseKey":"6:110","pageNumber":141,"lineNumber":14,"position":1,"charType":"word","location":"6:110:1","textUthmani":"وَنُقَلِّبُ","textQpcHafs":"وَنُقَلِّبُ","textIndopak":"وَنُقَلِّبُ","codeV1":"ﰀ","codeV2":"ﳏ"},{"id":74096,"verseKey":"6:110","pageNumber":141,"lineNumber":14,"position":2,"charType":"word","location":"6:110:2","textUthmani":"أَفْـِٔدَتَهُمْ","textQpcHafs":"أَفۡـِٔدَتَهُمۡ","textIndopak":"اَفۡـــِٕدَتَهُمۡ","codeV1":"ﰁ","codeV2":"ﳐ"},{"id":74097,"verseKey":"6:110","pageNumber":141,"lineNumber":14,"position":3,"charType":"word","location":"6:110:3","textUthmani":"وَأَبْصَـٰرَهُمْ","textQpcHafs":"وَأَبۡصَٰرَهُمۡ","textIndopak":"وَاَبۡصَارَهُمۡ","codeV1":"ﰂ","codeV2":"ﳑ"},{"id":74098,"verseKey":"6:110","pageNumber":141,"lineNumber":14,"position":4,"charType":"word","location":"6:110:4","textUthmani":"كَمَا","textQpcHafs":"كَمَا","textIndopak":"كَمَا","codeV1":"ﰃ","codeV2":"ﳒ"},{"id":74099,"verseKey":"6:110","pageNumber":141,"lineNumber":14,"position":5,"charType":"word","location":"6:110:5","textUthmani":"لَمْ","textQpcHafs":"لَمۡ","textIndopak":"لَمۡ","codeV1":"ﰄ","codeV2":"ﳓ"},{"id":74100,"verseKey":"6:110","pageNumber":141,"lineNumber":15,"position":6,"charType":"word","location":"6:110:6","textUthmani":"يُؤْمِنُوا۟","textQpcHafs":"يُؤۡمِنُواْ","textIndopak":"يُؤۡمِنُوۡا","codeV1":"ﰅ","codeV2":"ﳔ"},{"id":74101,"verseKey":"6:110","pageNumber":141,"lineNumber":15,"position":7,"charType":"word","location":"6:110:7","textUthmani":"بِهِۦٓ","textQpcHafs":"بِهِۦٓ","textIndopak":"بِهٖۤ","codeV1":"ﰆ","codeV2":"ﳕ"},{"id":74102,"verseKey":"6:110","pageNumber":141,"lineNumber":15,"position":8,"charType":"word","location":"6:110:8","textUthmani":"أَوَّلَ","textQpcHafs":"أَوَّلَ","textIndopak":"اَوَّلَ","codeV1":"ﰇ","codeV2":"ﳖ"},{"id":74103,"verseKey":"6:110","pageNumber":141,"lineNumber":15,"position":9,"charType":"word","location":"6:110:9","textUthmani":"مَرَّةٍۢ","textQpcHafs":"مَرَّةٖ","textIndopak":"مَرَّةٍ","codeV1":"ﰈ","codeV2":"ﳗ"},{"id":74104,"verseKey":"6:110","pageNumber":141,"lineNumber":15,"position":10,"charType":"word","location":"6:110:10","textUthmani":"وَنَذَرُهُمْ","textQpcHafs":"وَنَذَرُهُمۡ","textIndopak":"وَّنَذَرُهُمۡ","codeV1":"ﰉ","codeV2":"ﳘ"},{"id":74105,"verseKey":"6:110","pageNumber":141,"lineNumber":15,"position":11,"charType":"word","location":"6:110:11","textUthmani":"فِى","textQpcHafs":"فِي","textIndopak":"فِىۡ","codeV1":"ﰊ","codeV2":"ﳙ"},{"id":74106,"verseKey":"6:110","pageNumber":141,"lineNumber":15,"position":12,"charType":"word","location":"6:110:12","textUthmani":"طُغْيَـٰنِهِمْ","textQpcHafs":"طُغۡيَٰنِهِمۡ","textIndopak":"طُغۡيَانِهِمۡ","codeV1":"ﰋ","codeV2":"ﳚ"},{"id":74107,"verseKey":"6:110","pageNumber":141,"lineNumber":15,"position":13,"charType":"word","location":"6:110:13","textUthmani":"يَعْمَهُونَ","textQpcHafs":"يَعۡمَهُونَ","textIndopak":"يَعۡمَهُوۡنَ‏","codeV1":"ﰌ","codeV2":"ﳛ"},{"id":74108,"verseKey":"6:110","pageNumber":141,"lineNumber":15,"position":14,"charType":"end","location":"6:110:14","textUthmani":"١١٠","textQpcHafs":"١١٠","textIndopak":"١١٠","codeV1":"ﰍ","codeV2":"ﳜ"}]}]}